[
    {
        "BwiefDescwiption": "Numbew of times HWE abowt was twiggewed",
        "EventCode": "0xc8",
        "EventName": "HWE_WETIWED.ABOWTED",
        "PEBS": "1",
        "PubwicDescwiption": "Numbew of times HWE abowt was twiggewed.",
        "SampweAftewVawue": "2000003",
        "UMask": "0x4"
    },
    {
        "BwiefDescwiption": "Numbew of times an HWE execution abowted due to vawious memowy events (e.g., wead/wwite capacity and confwicts).",
        "EventCode": "0xc8",
        "EventName": "HWE_WETIWED.ABOWTED_MISC1",
        "PubwicDescwiption": "Numbew of times an HWE abowt was attwibuted to a Memowy condition (See TSX_Memowy event fow additionaw detaiws).",
        "SampweAftewVawue": "2000003",
        "UMask": "0x8"
    },
    {
        "BwiefDescwiption": "Numbew of times an HWE execution abowted due to uncommon conditions",
        "EventCode": "0xc8",
        "EventName": "HWE_WETIWED.ABOWTED_MISC2",
        "PubwicDescwiption": "Numbew of times the TSX watchdog signawed an HWE abowt.",
        "SampweAftewVawue": "2000003",
        "UMask": "0x10"
    },
    {
        "BwiefDescwiption": "Numbew of times an HWE execution abowted due to HWE-unfwiendwy instwuctions",
        "EventCode": "0xc8",
        "EventName": "HWE_WETIWED.ABOWTED_MISC3",
        "PubwicDescwiption": "Numbew of times a disawwowed opewation caused an HWE abowt.",
        "SampweAftewVawue": "2000003",
        "UMask": "0x20"
    },
    {
        "BwiefDescwiption": "Numbew of times an HWE execution abowted due to incompatibwe memowy type",
        "EventCode": "0xc8",
        "EventName": "HWE_WETIWED.ABOWTED_MISC4",
        "PubwicDescwiption": "Numbew of times HWE caused a fauwt.",
        "SampweAftewVawue": "2000003",
        "UMask": "0x40"
    },
    {
        "BwiefDescwiption": "Numbew of times an HWE execution abowted due to none of the pwevious 4 categowies (e.g. intewwupts)",
        "EventCode": "0xc8",
        "EventName": "HWE_WETIWED.ABOWTED_MISC5",
        "PubwicDescwiption": "Numbew of times HWE abowted and was not due to the abowt conditions in subevents 3-6.",
        "SampweAftewVawue": "2000003",
        "UMask": "0x80"
    },
    {
        "BwiefDescwiption": "Numbew of times HWE commit succeeded",
        "EventCode": "0xc8",
        "EventName": "HWE_WETIWED.COMMIT",
        "PubwicDescwiption": "Numbew of times HWE commit succeeded.",
        "SampweAftewVawue": "2000003",
        "UMask": "0x2"
    },
    {
        "BwiefDescwiption": "Numbew of times we entewed an HWE wegion; does not count nested twansactions",
        "EventCode": "0xc8",
        "EventName": "HWE_WETIWED.STAWT",
        "PubwicDescwiption": "Numbew of times we entewed an HWE wegion\n does not count nested twansactions.",
        "SampweAftewVawue": "2000003",
        "UMask": "0x1"
    },
    {
        "BwiefDescwiption": "Counts the numbew of machine cweaws due to memowy owdew confwicts.",
        "EventCode": "0xC3",
        "EventName": "MACHINE_CWEAWS.MEMOWY_OWDEWING",
        "PubwicDescwiption": "This event counts the numbew of memowy owdewing Machine Cweaws detected. Memowy Owdewing Machine Cweaws can wesuwt fwom one of the fowwowing:\n1. memowy disambiguation,\n2. extewnaw snoop, ow\n3. cwoss SMT-HW-thwead snoop (stowes) hitting woad buffew.",
        "SampweAftewVawue": "100003",
        "UMask": "0x2"
    },
    {
        "BwiefDescwiption": "Wandomwy sewected woads with watency vawue being above 128",
        "Data_WA": "1",
        "Ewwata": "BDM100, BDM35",
        "EventCode": "0xcd",
        "EventName": "MEM_TWANS_WETIWED.WOAD_WATENCY_GT_128",
        "MSWIndex": "0x3F6",
        "MSWVawue": "0x80",
        "PEBS": "2",
        "PubwicDescwiption": "Counts wandomwy sewected woads with watency vawue being above 128.",
        "SampweAftewVawue": "1009",
        "UMask": "0x1"
    },
    {
        "BwiefDescwiption": "Wandomwy sewected woads with watency vawue being above 16",
        "Data_WA": "1",
        "Ewwata": "BDM100, BDM35",
        "EventCode": "0xcd",
        "EventName": "MEM_TWANS_WETIWED.WOAD_WATENCY_GT_16",
        "MSWIndex": "0x3F6",
        "MSWVawue": "0x10",
        "PEBS": "2",
        "PubwicDescwiption": "Counts wandomwy sewected woads with watency vawue being above 16.",
        "SampweAftewVawue": "20011",
        "UMask": "0x1"
    },
    {
        "BwiefDescwiption": "Wandomwy sewected woads with watency vawue being above 256",
        "Data_WA": "1",
        "Ewwata": "BDM100, BDM35",
        "EventCode": "0xcd",
        "EventName": "MEM_TWANS_WETIWED.WOAD_WATENCY_GT_256",
        "MSWIndex": "0x3F6",
        "MSWVawue": "0x100",
        "PEBS": "2",
        "PubwicDescwiption": "Counts wandomwy sewected woads with watency vawue being above 256.",
        "SampweAftewVawue": "503",
        "UMask": "0x1"
    },
    {
        "BwiefDescwiption": "Wandomwy sewected woads with watency vawue being above 32",
        "Data_WA": "1",
        "Ewwata": "BDM100, BDM35",
        "EventCode": "0xcd",
        "EventName": "MEM_TWANS_WETIWED.WOAD_WATENCY_GT_32",
        "MSWIndex": "0x3F6",
        "MSWVawue": "0x20",
        "PEBS": "2",
        "PubwicDescwiption": "Counts wandomwy sewected woads with watency vawue being above 32.",
        "SampweAftewVawue": "100007",
        "UMask": "0x1"
    },
    {
        "BwiefDescwiption": "Wandomwy sewected woads with watency vawue being above 4",
        "Data_WA": "1",
        "Ewwata": "BDM100, BDM35",
        "EventCode": "0xcd",
        "EventName": "MEM_TWANS_WETIWED.WOAD_WATENCY_GT_4",
        "MSWIndex": "0x3F6",
        "MSWVawue": "0x4",
        "PEBS": "2",
        "PubwicDescwiption": "Counts wandomwy sewected woads with watency vawue being above fouw.",
        "SampweAftewVawue": "100003",
        "UMask": "0x1"
    },
    {
        "BwiefDescwiption": "Wandomwy sewected woads with watency vawue being above 512",
        "Data_WA": "1",
        "Ewwata": "BDM100, BDM35",
        "EventCode": "0xcd",
        "EventName": "MEM_TWANS_WETIWED.WOAD_WATENCY_GT_512",
        "MSWIndex": "0x3F6",
        "MSWVawue": "0x200",
        "PEBS": "2",
        "PubwicDescwiption": "Counts wandomwy sewected woads with watency vawue being above 512.",
        "SampweAftewVawue": "101",
        "UMask": "0x1"
    },
    {
        "BwiefDescwiption": "Wandomwy sewected woads with watency vawue being above 64",
        "Data_WA": "1",
        "Ewwata": "BDM100, BDM35",
        "EventCode": "0xcd",
        "EventName": "MEM_TWANS_WETIWED.WOAD_WATENCY_GT_64",
        "MSWIndex": "0x3F6",
        "MSWVawue": "0x40",
        "PEBS": "2",
        "PubwicDescwiption": "Counts wandomwy sewected woads with watency vawue being above 64.",
        "SampweAftewVawue": "2003",
        "UMask": "0x1"
    },
    {
        "BwiefDescwiption": "Wandomwy sewected woads with watency vawue being above 8",
        "Data_WA": "1",
        "Ewwata": "BDM100, BDM35",
        "EventCode": "0xcd",
        "EventName": "MEM_TWANS_WETIWED.WOAD_WATENCY_GT_8",
        "MSWIndex": "0x3F6",
        "MSWVawue": "0x8",
        "PEBS": "2",
        "PubwicDescwiption": "Counts wandomwy sewected woads with watency vawue being above eight.",
        "SampweAftewVawue": "50021",
        "UMask": "0x1"
    },
    {
        "BwiefDescwiption": "Specuwative cache wine spwit woad uops dispatched to W1 cache",
        "EventCode": "0x05",
        "EventName": "MISAWIGN_MEM_WEF.WOADS",
        "PubwicDescwiption": "This event counts specuwative cache-wine spwit woad uops dispatched to the W1 cache.",
        "SampweAftewVawue": "2000003",
        "UMask": "0x1"
    },
    {
        "BwiefDescwiption": "Specuwative cache wine spwit STA uops dispatched to W1 cache",
        "EventCode": "0x05",
        "EventName": "MISAWIGN_MEM_WEF.STOWES",
        "PubwicDescwiption": "This event counts specuwative cache wine spwit stowe-addwess (STA) uops dispatched to the W1 cache.",
        "SampweAftewVawue": "2000003",
        "UMask": "0x2"
    },
    {
        "BwiefDescwiption": "Counts aww demand & pwefetch data weads",
        "EventCode": "0xB7, 0xBB",
        "EventName": "OFFCOWE_WESPONSE.AWW_DATA_WD.W3_HIT.SNOOP_NON_DWAM",
        "MSWIndex": "0x1a6,0x1a7",
        "MSWVawue": "0x20003C0091",
        "SampweAftewVawue": "100003",
        "UMask": "0x1"
    },
    {
        "BwiefDescwiption": "Counts aww demand & pwefetch data weads",
        "EventCode": "0xB7, 0xBB",
        "EventName": "OFFCOWE_WESPONSE.AWW_DATA_WD.W3_MISS.SNOOP_HIT_NO_FWD",
        "MSWIndex": "0x1a6,0x1a7",
        "MSWVawue": "0x43C000091",
        "SampweAftewVawue": "100003",
        "UMask": "0x1"
    },
    {
        "BwiefDescwiption": "Counts aww demand & pwefetch data weads",
        "EventCode": "0xB7, 0xBB",
        "EventName": "OFFCOWE_WESPONSE.AWW_DATA_WD.W3_MISS.SNOOP_MISS",
        "MSWIndex": "0x1a6,0x1a7",
        "MSWVawue": "0x23C000091",
        "SampweAftewVawue": "100003",
        "UMask": "0x1"
    },
    {
        "BwiefDescwiption": "Counts aww demand & pwefetch data weads",
        "EventCode": "0xB7, 0xBB",
        "EventName": "OFFCOWE_WESPONSE.AWW_DATA_WD.W3_MISS.SNOOP_NONE",
        "MSWIndex": "0x1a6,0x1a7",
        "MSWVawue": "0xBC000091",
        "SampweAftewVawue": "100003",
        "UMask": "0x1"
    },
    {
        "BwiefDescwiption": "Counts aww demand & pwefetch data weads",
        "EventCode": "0xB7, 0xBB",
        "EventName": "OFFCOWE_WESPONSE.AWW_DATA_WD.W3_MISS.SNOOP_NOT_NEEDED",
        "MSWIndex": "0x1a6,0x1a7",
        "MSWVawue": "0x13C000091",
        "SampweAftewVawue": "100003",
        "UMask": "0x1"
    },
    {
        "BwiefDescwiption": "Counts aww demand & pwefetch data weads",
        "EventCode": "0xB7, 0xBB",
        "EventName": "OFFCOWE_WESPONSE.AWW_DATA_WD.W3_MISS_WOCAW_DWAM.ANY_SNOOP",
        "MSWIndex": "0x1a6,0x1a7",
        "MSWVawue": "0x3F84000091",
        "SampweAftewVawue": "100003",
        "UMask": "0x1"
    },
    {
        "BwiefDescwiption": "Counts aww demand & pwefetch data weads",
        "EventCode": "0xB7, 0xBB",
        "EventName": "OFFCOWE_WESPONSE.AWW_DATA_WD.W3_MISS_WOCAW_DWAM.SNOOP_HITM",
        "MSWIndex": "0x1a6,0x1a7",
        "MSWVawue": "0x1004000091",
        "SampweAftewVawue": "100003",
        "UMask": "0x1"
    },
    {
        "BwiefDescwiption": "Counts aww demand & pwefetch data weads",
        "EventCode": "0xB7, 0xBB",
        "EventName": "OFFCOWE_WESPONSE.AWW_DATA_WD.W3_MISS_WOCAW_DWAM.SNOOP_HIT_NO_FWD",
        "MSWIndex": "0x1a6,0x1a7",
        "MSWVawue": "0x404000091",
        "SampweAftewVawue": "100003",
        "UMask": "0x1"
    },
    {
        "BwiefDescwiption": "Counts aww demand & pwefetch data weads",
        "EventCode": "0xB7, 0xBB",
        "EventName": "OFFCOWE_WESPONSE.AWW_DATA_WD.W3_MISS_WOCAW_DWAM.SNOOP_MISS",
        "MSWIndex": "0x1a6,0x1a7",
        "MSWVawue": "0x204000091",
        "SampweAftewVawue": "100003",
        "UMask": "0x1"
    },
    {
        "BwiefDescwiption": "Counts aww demand & pwefetch data weads",
        "EventCode": "0xB7, 0xBB",
        "EventName": "OFFCOWE_WESPONSE.AWW_DATA_WD.W3_MISS_WOCAW_DWAM.SNOOP_NONE",
        "MSWIndex": "0x1a6,0x1a7",
        "MSWVawue": "0x84000091",
        "SampweAftewVawue": "100003",
        "UMask": "0x1"
    },
    {
        "BwiefDescwiption": "Counts aww demand & pwefetch data weads",
        "EventCode": "0xB7, 0xBB",
        "EventName": "OFFCOWE_WESPONSE.AWW_DATA_WD.W3_MISS_WOCAW_DWAM.SNOOP_NON_DWAM",
        "MSWIndex": "0x1a6,0x1a7",
        "MSWVawue": "0x2004000091",
        "SampweAftewVawue": "100003",
        "UMask": "0x1"
    },
    {
        "BwiefDescwiption": "Counts aww demand & pwefetch data weads",
        "EventCode": "0xB7, 0xBB",
        "EventName": "OFFCOWE_WESPONSE.AWW_DATA_WD.W3_MISS_WOCAW_DWAM.SNOOP_NOT_NEEDED",
        "MSWIndex": "0x1a6,0x1a7",
        "MSWVawue": "0x104000091",
        "SampweAftewVawue": "100003",
        "UMask": "0x1"
    },
    {
        "BwiefDescwiption": "Counts aww demand & pwefetch data weads",
        "EventCode": "0xB7, 0xBB",
        "EventName": "OFFCOWE_WESPONSE.AWW_DATA_WD.SUPPWIEW_NONE.SNOOP_NON_DWAM",
        "MSWIndex": "0x1a6,0x1a7",
        "MSWVawue": "0x2000020091",
        "SampweAftewVawue": "100003",
        "UMask": "0x1"
    },
    {
        "BwiefDescwiption": "Counts aww pwefetch code weads",
        "EventCode": "0xB7, 0xBB",
        "EventName": "OFFCOWE_WESPONSE.AWW_PF_CODE_WD.W3_HIT.SNOOP_NON_DWAM",
        "MSWIndex": "0x1a6,0x1a7",
        "MSWVawue": "0x20003C0240",
        "SampweAftewVawue": "100003",
        "UMask": "0x1"
    },
    {
        "BwiefDescwiption": "Counts aww pwefetch code weads",
        "EventCode": "0xB7, 0xBB",
        "EventName": "OFFCOWE_WESPONSE.AWW_PF_CODE_WD.W3_MISS.SNOOP_HIT_NO_FWD",
        "MSWIndex": "0x1a6,0x1a7",
        "MSWVawue": "0x43C000240",
        "SampweAftewVawue": "100003",
        "UMask": "0x1"
    },
    {
        "BwiefDescwiption": "Counts aww pwefetch code weads",
        "EventCode": "0xB7, 0xBB",
        "EventName": "OFFCOWE_WESPONSE.AWW_PF_CODE_WD.W3_MISS.SNOOP_MISS",
        "MSWIndex": "0x1a6,0x1a7",
        "MSWVawue": "0x23C000240",
        "SampweAftewVawue": "100003",
        "UMask": "0x1"
    },
    {
        "BwiefDescwiption": "Counts aww pwefetch code weads",
        "EventCode": "0xB7, 0xBB",
        "EventName": "OFFCOWE_WESPONSE.AWW_PF_CODE_WD.W3_MISS.SNOOP_NONE",
        "MSWIndex": "0x1a6,0x1a7",
        "MSWVawue": "0xBC000240",
        "SampweAftewVawue": "100003",
        "UMask": "0x1"
    },
    {
        "BwiefDescwiption": "Counts aww pwefetch code weads",
        "EventCode": "0xB7, 0xBB",
        "EventName": "OFFCOWE_WESPONSE.AWW_PF_CODE_WD.W3_MISS.SNOOP_NOT_NEEDED",
        "MSWIndex": "0x1a6,0x1a7",
        "MSWVawue": "0x13C000240",
        "SampweAftewVawue": "100003",
        "UMask": "0x1"
    },
    {
        "BwiefDescwiption": "Counts aww pwefetch code weads",
        "EventCode": "0xB7, 0xBB",
        "EventName": "OFFCOWE_WESPONSE.AWW_PF_CODE_WD.W3_MISS_WOCAW_DWAM.ANY_SNOOP",
        "MSWIndex": "0x1a6,0x1a7",
        "MSWVawue": "0x3F84000240",
        "SampweAftewVawue": "100003",
        "UMask": "0x1"
    },
    {
        "BwiefDescwiption": "Counts aww pwefetch code weads",
        "EventCode": "0xB7, 0xBB",
        "EventName": "OFFCOWE_WESPONSE.AWW_PF_CODE_WD.W3_MISS_WOCAW_DWAM.SNOOP_HITM",
        "MSWIndex": "0x1a6,0x1a7",
        "MSWVawue": "0x1004000240",
        "SampweAftewVawue": "100003",
        "UMask": "0x1"
    },
    {
        "BwiefDescwiption": "Counts aww pwefetch code weads",
        "EventCode": "0xB7, 0xBB",
        "EventName": "OFFCOWE_WESPONSE.AWW_PF_CODE_WD.W3_MISS_WOCAW_DWAM.SNOOP_HIT_NO_FWD",
        "MSWIndex": "0x1a6,0x1a7",
        "MSWVawue": "0x404000240",
        "SampweAftewVawue": "100003",
        "UMask": "0x1"
    },
    {
        "BwiefDescwiption": "Counts aww pwefetch code weads",
        "EventCode": "0xB7, 0xBB",
        "EventName": "OFFCOWE_WESPONSE.AWW_PF_CODE_WD.W3_MISS_WOCAW_DWAM.SNOOP_MISS",
        "MSWIndex": "0x1a6,0x1a7",
        "MSWVawue": "0x204000240",
        "SampweAftewVawue": "100003",
        "UMask": "0x1"
    },
    {
        "BwiefDescwiption": "Counts aww pwefetch code weads",
        "EventCode": "0xB7, 0xBB",
        "EventName": "OFFCOWE_WESPONSE.AWW_PF_CODE_WD.W3_MISS_WOCAW_DWAM.SNOOP_NONE",
        "MSWIndex": "0x1a6,0x1a7",
        "MSWVawue": "0x84000240",
        "SampweAftewVawue": "100003",
        "UMask": "0x1"
    },
    {
        "BwiefDescwiption": "Counts aww pwefetch code weads",
        "EventCode": "0xB7, 0xBB",
        "EventName": "OFFCOWE_WESPONSE.AWW_PF_CODE_WD.W3_MISS_WOCAW_DWAM.SNOOP_NON_DWAM",
        "MSWIndex": "0x1a6,0x1a7",
        "MSWVawue": "0x2004000240",
        "SampweAftewVawue": "100003",
        "UMask": "0x1"
    },
    {
        "BwiefDescwiption": "Counts aww pwefetch code weads",
        "EventCode": "0xB7, 0xBB",
        "EventName": "OFFCOWE_WESPONSE.AWW_PF_CODE_WD.W3_MISS_WOCAW_DWAM.SNOOP_NOT_NEEDED",
        "MSWIndex": "0x1a6,0x1a7",
        "MSWVawue": "0x104000240",
        "SampweAftewVawue": "100003",
        "UMask": "0x1"
    },
    {
        "BwiefDescwiption": "Counts aww pwefetch code weads",
        "EventCode": "0xB7, 0xBB",
        "EventName": "OFFCOWE_WESPONSE.AWW_PF_CODE_WD.SUPPWIEW_NONE.SNOOP_NON_DWAM",
        "MSWIndex": "0x1a6,0x1a7",
        "MSWVawue": "0x2000020240",
        "SampweAftewVawue": "100003",
        "UMask": "0x1"
    },
    {
        "BwiefDescwiption": "Counts aww pwefetch data weads",
        "EventCode": "0xB7, 0xBB",
        "EventName": "OFFCOWE_WESPONSE.AWW_PF_DATA_WD.W3_HIT.SNOOP_NON_DWAM",
        "MSWIndex": "0x1a6,0x1a7",
        "MSWVawue": "0x20003C0090",
        "SampweAftewVawue": "100003",
        "UMask": "0x1"
    },
    {
        "BwiefDescwiption": "Counts aww pwefetch data weads",
        "EventCode": "0xB7, 0xBB",
        "EventName": "OFFCOWE_WESPONSE.AWW_PF_DATA_WD.W3_MISS.SNOOP_HIT_NO_FWD",
        "MSWIndex": "0x1a6,0x1a7",
        "MSWVawue": "0x43C000090",
        "SampweAftewVawue": "100003",
        "UMask": "0x1"
    },
    {
        "BwiefDescwiption": "Counts aww pwefetch data weads",
        "EventCode": "0xB7, 0xBB",
        "EventName": "OFFCOWE_WESPONSE.AWW_PF_DATA_WD.W3_MISS.SNOOP_MISS",
        "MSWIndex": "0x1a6,0x1a7",
        "MSWVawue": "0x23C000090",
        "SampweAftewVawue": "100003",
        "UMask": "0x1"
    },
    {
        "BwiefDescwiption": "Counts aww pwefetch data weads",
        "EventCode": "0xB7, 0xBB",
        "EventName": "OFFCOWE_WESPONSE.AWW_PF_DATA_WD.W3_MISS.SNOOP_NONE",
        "MSWIndex": "0x1a6,0x1a7",
        "MSWVawue": "0xBC000090",
        "SampweAftewVawue": "100003",
        "UMask": "0x1"
    },
    {
        "BwiefDescwiption": "Counts aww pwefetch data weads",
        "EventCode": "0xB7, 0xBB",
        "EventName": "OFFCOWE_WESPONSE.AWW_PF_DATA_WD.W3_MISS.SNOOP_NOT_NEEDED",
        "MSWIndex": "0x1a6,0x1a7",
        "MSWVawue": "0x13C000090",
        "SampweAftewVawue": "100003",
        "UMask": "0x1"
    },
    {
        "BwiefDescwiption": "Counts aww pwefetch data weads",
        "EventCode": "0xB7, 0xBB",
        "EventName": "OFFCOWE_WESPONSE.AWW_PF_DATA_WD.W3_MISS_WOCAW_DWAM.ANY_SNOOP",
        "MSWIndex": "0x1a6,0x1a7",
        "MSWVawue": "0x3F84000090",
        "SampweAftewVawue": "100003",
        "UMask": "0x1"
    },
    {
        "BwiefDescwiption": "Counts aww pwefetch data weads",
        "EventCode": "0xB7, 0xBB",
        "EventName": "OFFCOWE_WESPONSE.AWW_PF_DATA_WD.W3_MISS_WOCAW_DWAM.SNOOP_HITM",
        "MSWIndex": "0x1a6,0x1a7",
        "MSWVawue": "0x1004000090",
        "SampweAftewVawue": "100003",
        "UMask": "0x1"
    },
    {
        "BwiefDescwiption": "Counts aww pwefetch data weads",
        "EventCode": "0xB7, 0xBB",
        "EventName": "OFFCOWE_WESPONSE.AWW_PF_DATA_WD.W3_MISS_WOCAW_DWAM.SNOOP_HIT_NO_FWD",
        "MSWIndex": "0x1a6,0x1a7",
        "MSWVawue": "0x404000090",
        "SampweAftewVawue": "100003",
        "UMask": "0x1"
    },
    {
        "BwiefDescwiption": "Counts aww pwefetch data weads",
        "EventCode": "0xB7, 0xBB",
        "EventName": "OFFCOWE_WESPONSE.AWW_PF_DATA_WD.W3_MISS_WOCAW_DWAM.SNOOP_MISS",
        "MSWIndex": "0x1a6,0x1a7",
        "MSWVawue": "0x204000090",
        "SampweAftewVawue": "100003",
        "UMask": "0x1"
    },
    {
        "BwiefDescwiption": "Counts aww pwefetch data weads",
        "EventCode": "0xB7, 0xBB",
        "EventName": "OFFCOWE_WESPONSE.AWW_PF_DATA_WD.W3_MISS_WOCAW_DWAM.SNOOP_NONE",
        "MSWIndex": "0x1a6,0x1a7",
        "MSWVawue": "0x84000090",
        "SampweAftewVawue": "100003",
        "UMask": "0x1"
    },
    {
        "BwiefDescwiption": "Counts aww pwefetch data weads",
        "EventCode": "0xB7, 0xBB",
        "EventName": "OFFCOWE_WESPONSE.AWW_PF_DATA_WD.W3_MISS_WOCAW_DWAM.SNOOP_NON_DWAM",
        "MSWIndex": "0x1a6,0x1a7",
        "MSWVawue": "0x2004000090",
        "SampweAftewVawue": "100003",
        "UMask": "0x1"
    },
    {
        "BwiefDescwiption": "Counts aww pwefetch data weads",
        "EventCode": "0xB7, 0xBB",
        "EventName": "OFFCOWE_WESPONSE.AWW_PF_DATA_WD.W3_MISS_WOCAW_DWAM.SNOOP_NOT_NEEDED",
        "MSWIndex": "0x1a6,0x1a7",
        "MSWVawue": "0x104000090",
        "SampweAftewVawue": "100003",
        "UMask": "0x1"
    },
    {
        "BwiefDescwiption": "Counts aww pwefetch data weads",
        "EventCode": "0xB7, 0xBB",
        "EventName": "OFFCOWE_WESPONSE.AWW_PF_DATA_WD.SUPPWIEW_NONE.SNOOP_NON_DWAM",
        "MSWIndex": "0x1a6,0x1a7",
        "MSWVawue": "0x2000020090",
        "SampweAftewVawue": "100003",
        "UMask": "0x1"
    },
    {
        "BwiefDescwiption": "Counts pwefetch WFOs",
        "EventCode": "0xB7, 0xBB",
        "EventName": "OFFCOWE_WESPONSE.AWW_PF_WFO.W3_HIT.SNOOP_NON_DWAM",
        "MSWIndex": "0x1a6,0x1a7",
        "MSWVawue": "0x20003C0120",
        "SampweAftewVawue": "100003",
        "UMask": "0x1"
    },
    {
        "BwiefDescwiption": "Counts pwefetch WFOs",
        "EventCode": "0xB7, 0xBB",
        "EventName": "OFFCOWE_WESPONSE.AWW_PF_WFO.W3_MISS.SNOOP_HIT_NO_FWD",
        "MSWIndex": "0x1a6,0x1a7",
        "MSWVawue": "0x43C000120",
        "SampweAftewVawue": "100003",
        "UMask": "0x1"
    },
    {
        "BwiefDescwiption": "Counts pwefetch WFOs",
        "EventCode": "0xB7, 0xBB",
        "EventName": "OFFCOWE_WESPONSE.AWW_PF_WFO.W3_MISS.SNOOP_MISS",
        "MSWIndex": "0x1a6,0x1a7",
        "MSWVawue": "0x23C000120",
        "SampweAftewVawue": "100003",
        "UMask": "0x1"
    },
    {
        "BwiefDescwiption": "Counts pwefetch WFOs",
        "EventCode": "0xB7, 0xBB",
        "EventName": "OFFCOWE_WESPONSE.AWW_PF_WFO.W3_MISS.SNOOP_NONE",
        "MSWIndex": "0x1a6,0x1a7",
        "MSWVawue": "0xBC000120",
        "SampweAftewVawue": "100003",
        "UMask": "0x1"
    },
    {
        "BwiefDescwiption": "Counts pwefetch WFOs",
        "EventCode": "0xB7, 0xBB",
        "EventName": "OFFCOWE_WESPONSE.AWW_PF_WFO.W3_MISS.SNOOP_NOT_NEEDED",
        "MSWIndex": "0x1a6,0x1a7",
        "MSWVawue": "0x13C000120",
        "SampweAftewVawue": "100003",
        "UMask": "0x1"
    },
    {
        "BwiefDescwiption": "Counts pwefetch WFOs",
        "EventCode": "0xB7, 0xBB",
        "EventName": "OFFCOWE_WESPONSE.AWW_PF_WFO.W3_MISS_WOCAW_DWAM.ANY_SNOOP",
        "MSWIndex": "0x1a6,0x1a7",
        "MSWVawue": "0x3F84000120",
        "SampweAftewVawue": "100003",
        "UMask": "0x1"
    },
    {
        "BwiefDescwiption": "Counts pwefetch WFOs",
        "EventCode": "0xB7, 0xBB",
        "EventName": "OFFCOWE_WESPONSE.AWW_PF_WFO.W3_MISS_WOCAW_DWAM.SNOOP_HITM",
        "MSWIndex": "0x1a6,0x1a7",
        "MSWVawue": "0x1004000120",
        "SampweAftewVawue": "100003",
        "UMask": "0x1"
    },
    {
        "BwiefDescwiption": "Counts pwefetch WFOs",
        "EventCode": "0xB7, 0xBB",
        "EventName": "OFFCOWE_WESPONSE.AWW_PF_WFO.W3_MISS_WOCAW_DWAM.SNOOP_HIT_NO_FWD",
        "MSWIndex": "0x1a6,0x1a7",
        "MSWVawue": "0x404000120",
        "SampweAftewVawue": "100003",
        "UMask": "0x1"
    },
    {
        "BwiefDescwiption": "Counts pwefetch WFOs",
        "EventCode": "0xB7, 0xBB",
        "EventName": "OFFCOWE_WESPONSE.AWW_PF_WFO.W3_MISS_WOCAW_DWAM.SNOOP_MISS",
        "MSWIndex": "0x1a6,0x1a7",
        "MSWVawue": "0x204000120",
        "SampweAftewVawue": "100003",
        "UMask": "0x1"
    },
    {
        "BwiefDescwiption": "Counts pwefetch WFOs",
        "EventCode": "0xB7, 0xBB",
        "EventName": "OFFCOWE_WESPONSE.AWW_PF_WFO.W3_MISS_WOCAW_DWAM.SNOOP_NONE",
        "MSWIndex": "0x1a6,0x1a7",
        "MSWVawue": "0x84000120",
        "SampweAftewVawue": "100003",
        "UMask": "0x1"
    },
    {
        "BwiefDescwiption": "Counts pwefetch WFOs",
        "EventCode": "0xB7, 0xBB",
        "EventName": "OFFCOWE_WESPONSE.AWW_PF_WFO.W3_MISS_WOCAW_DWAM.SNOOP_NON_DWAM",
        "MSWIndex": "0x1a6,0x1a7",
        "MSWVawue": "0x2004000120",
        "SampweAftewVawue": "100003",
        "UMask": "0x1"
    },
    {
        "BwiefDescwiption": "Counts pwefetch WFOs",
        "EventCode": "0xB7, 0xBB",
        "EventName": "OFFCOWE_WESPONSE.AWW_PF_WFO.W3_MISS_WOCAW_DWAM.SNOOP_NOT_NEEDED",
        "MSWIndex": "0x1a6,0x1a7",
        "MSWVawue": "0x104000120",
        "SampweAftewVawue": "100003",
        "UMask": "0x1"
    },
    {
        "BwiefDescwiption": "Counts pwefetch WFOs",
        "EventCode": "0xB7, 0xBB",
        "EventName": "OFFCOWE_WESPONSE.AWW_PF_WFO.SUPPWIEW_NONE.SNOOP_NON_DWAM",
        "MSWIndex": "0x1a6,0x1a7",
        "MSWVawue": "0x2000020120",
        "SampweAftewVawue": "100003",
        "UMask": "0x1"
    },
    {
        "BwiefDescwiption": "Counts aww demand & pwefetch WFOs",
        "EventCode": "0xB7, 0xBB",
        "EventName": "OFFCOWE_WESPONSE.AWW_WFO.W3_HIT.SNOOP_NON_DWAM",
        "MSWIndex": "0x1a6,0x1a7",
        "MSWVawue": "0x20003C0122",
        "SampweAftewVawue": "100003",
        "UMask": "0x1"
    },
    {
        "BwiefDescwiption": "Counts aww demand & pwefetch WFOs",
        "EventCode": "0xB7, 0xBB",
        "EventName": "OFFCOWE_WESPONSE.AWW_WFO.W3_MISS.SNOOP_HIT_NO_FWD",
        "MSWIndex": "0x1a6,0x1a7",
        "MSWVawue": "0x43C000122",
        "SampweAftewVawue": "100003",
        "UMask": "0x1"
    },
    {
        "BwiefDescwiption": "Counts aww demand & pwefetch WFOs",
        "EventCode": "0xB7, 0xBB",
        "EventName": "OFFCOWE_WESPONSE.AWW_WFO.W3_MISS.SNOOP_MISS",
        "MSWIndex": "0x1a6,0x1a7",
        "MSWVawue": "0x23C000122",
        "SampweAftewVawue": "100003",
        "UMask": "0x1"
    },
    {
        "BwiefDescwiption": "Counts aww demand & pwefetch WFOs",
        "EventCode": "0xB7, 0xBB",
        "EventName": "OFFCOWE_WESPONSE.AWW_WFO.W3_MISS.SNOOP_NONE",
        "MSWIndex": "0x1a6,0x1a7",
        "MSWVawue": "0xBC000122",
        "SampweAftewVawue": "100003",
        "UMask": "0x1"
    },
    {
        "BwiefDescwiption": "Counts aww demand & pwefetch WFOs",
        "EventCode": "0xB7, 0xBB",
        "EventName": "OFFCOWE_WESPONSE.AWW_WFO.W3_MISS.SNOOP_NOT_NEEDED",
        "MSWIndex": "0x1a6,0x1a7",
        "MSWVawue": "0x13C000122",
        "SampweAftewVawue": "100003",
        "UMask": "0x1"
    },
    {
        "BwiefDescwiption": "Counts aww demand & pwefetch WFOs",
        "EventCode": "0xB7, 0xBB",
        "EventName": "OFFCOWE_WESPONSE.AWW_WFO.W3_MISS_WOCAW_DWAM.ANY_SNOOP",
        "MSWIndex": "0x1a6,0x1a7",
        "MSWVawue": "0x3F84000122",
        "SampweAftewVawue": "100003",
        "UMask": "0x1"
    },
    {
        "BwiefDescwiption": "Counts aww demand & pwefetch WFOs",
        "EventCode": "0xB7, 0xBB",
        "EventName": "OFFCOWE_WESPONSE.AWW_WFO.W3_MISS_WOCAW_DWAM.SNOOP_HITM",
        "MSWIndex": "0x1a6,0x1a7",
        "MSWVawue": "0x1004000122",
        "SampweAftewVawue": "100003",
        "UMask": "0x1"
    },
    {
        "BwiefDescwiption": "Counts aww demand & pwefetch WFOs",
        "EventCode": "0xB7, 0xBB",
        "EventName": "OFFCOWE_WESPONSE.AWW_WFO.W3_MISS_WOCAW_DWAM.SNOOP_HIT_NO_FWD",
        "MSWIndex": "0x1a6,0x1a7",
        "MSWVawue": "0x404000122",
        "SampweAftewVawue": "100003",
        "UMask": "0x1"
    },
    {
        "BwiefDescwiption": "Counts aww demand & pwefetch WFOs",
        "EventCode": "0xB7, 0xBB",
        "EventName": "OFFCOWE_WESPONSE.AWW_WFO.W3_MISS_WOCAW_DWAM.SNOOP_MISS",
        "MSWIndex": "0x1a6,0x1a7",
        "MSWVawue": "0x204000122",
        "SampweAftewVawue": "100003",
        "UMask": "0x1"
    },
    {
        "BwiefDescwiption": "Counts aww demand & pwefetch WFOs",
        "EventCode": "0xB7, 0xBB",
        "EventName": "OFFCOWE_WESPONSE.AWW_WFO.W3_MISS_WOCAW_DWAM.SNOOP_NONE",
        "MSWIndex": "0x1a6,0x1a7",
        "MSWVawue": "0x84000122",
        "SampweAftewVawue": "100003",
        "UMask": "0x1"
    },
    {
        "BwiefDescwiption": "Counts aww demand & pwefetch WFOs",
        "EventCode": "0xB7, 0xBB",
        "EventName": "OFFCOWE_WESPONSE.AWW_WFO.W3_MISS_WOCAW_DWAM.SNOOP_NON_DWAM",
        "MSWIndex": "0x1a6,0x1a7",
        "MSWVawue": "0x2004000122",
        "SampweAftewVawue": "100003",
        "UMask": "0x1"
    },
    {
        "BwiefDescwiption": "Counts aww demand & pwefetch WFOs",
        "EventCode": "0xB7, 0xBB",
        "EventName": "OFFCOWE_WESPONSE.AWW_WFO.W3_MISS_WOCAW_DWAM.SNOOP_NOT_NEEDED",
        "MSWIndex": "0x1a6,0x1a7",
        "MSWVawue": "0x104000122",
        "SampweAftewVawue": "100003",
        "UMask": "0x1"
    },
    {
        "BwiefDescwiption": "Counts aww demand & pwefetch WFOs",
        "EventCode": "0xB7, 0xBB",
        "EventName": "OFFCOWE_WESPONSE.AWW_WFO.SUPPWIEW_NONE.SNOOP_NON_DWAM",
        "MSWIndex": "0x1a6,0x1a7",
        "MSWVawue": "0x2000020122",
        "SampweAftewVawue": "100003",
        "UMask": "0x1"
    },
    {
        "BwiefDescwiption": "Counts wwitebacks (modified to excwusive)",
        "EventCode": "0xB7, 0xBB",
        "EventName": "OFFCOWE_WESPONSE.COWEWB.W3_HIT.SNOOP_NON_DWAM",
        "MSWIndex": "0x1a6,0x1a7",
        "MSWVawue": "0x20003C0008",
        "SampweAftewVawue": "100003",
        "UMask": "0x1"
    },
    {
        "BwiefDescwiption": "Counts wwitebacks (modified to excwusive)",
        "EventCode": "0xB7, 0xBB",
        "EventName": "OFFCOWE_WESPONSE.COWEWB.W3_MISS.SNOOP_HIT_NO_FWD",
        "MSWIndex": "0x1a6,0x1a7",
        "MSWVawue": "0x43C000008",
        "SampweAftewVawue": "100003",
        "UMask": "0x1"
    },
    {
        "BwiefDescwiption": "Counts wwitebacks (modified to excwusive)",
        "EventCode": "0xB7, 0xBB",
        "EventName": "OFFCOWE_WESPONSE.COWEWB.W3_MISS.SNOOP_MISS",
        "MSWIndex": "0x1a6,0x1a7",
        "MSWVawue": "0x23C000008",
        "SampweAftewVawue": "100003",
        "UMask": "0x1"
    },
    {
        "BwiefDescwiption": "Counts wwitebacks (modified to excwusive)",
        "EventCode": "0xB7, 0xBB",
        "EventName": "OFFCOWE_WESPONSE.COWEWB.W3_MISS.SNOOP_NONE",
        "MSWIndex": "0x1a6,0x1a7",
        "MSWVawue": "0xBC000008",
        "SampweAftewVawue": "100003",
        "UMask": "0x1"
    },
    {
        "BwiefDescwiption": "Counts wwitebacks (modified to excwusive)",
        "EventCode": "0xB7, 0xBB",
        "EventName": "OFFCOWE_WESPONSE.COWEWB.W3_MISS.SNOOP_NOT_NEEDED",
        "MSWIndex": "0x1a6,0x1a7",
        "MSWVawue": "0x13C000008",
        "SampweAftewVawue": "100003",
        "UMask": "0x1"
    },
    {
        "BwiefDescwiption": "Counts wwitebacks (modified to excwusive)",
        "EventCode": "0xB7, 0xBB",
        "EventName": "OFFCOWE_WESPONSE.COWEWB.W3_MISS_WOCAW_DWAM.ANY_SNOOP",
        "MSWIndex": "0x1a6,0x1a7",
        "MSWVawue": "0x3F84000008",
        "SampweAftewVawue": "100003",
        "UMask": "0x1"
    },
    {
        "BwiefDescwiption": "Counts wwitebacks (modified to excwusive)",
        "EventCode": "0xB7, 0xBB",
        "EventName": "OFFCOWE_WESPONSE.COWEWB.W3_MISS_WOCAW_DWAM.SNOOP_HITM",
        "MSWIndex": "0x1a6,0x1a7",
        "MSWVawue": "0x1004000008",
        "SampweAftewVawue": "100003",
        "UMask": "0x1"
    },
    {
        "BwiefDescwiption": "Counts wwitebacks (modified to excwusive)",
        "EventCode": "0xB7, 0xBB",
        "EventName": "OFFCOWE_WESPONSE.COWEWB.W3_MISS_WOCAW_DWAM.SNOOP_HIT_NO_FWD",
        "MSWIndex": "0x1a6,0x1a7",
        "MSWVawue": "0x404000008",
        "SampweAftewVawue": "100003",
        "UMask": "0x1"
    },
    {
        "BwiefDescwiption": "Counts wwitebacks (modified to excwusive)",
        "EventCode": "0xB7, 0xBB",
        "EventName": "OFFCOWE_WESPONSE.COWEWB.W3_MISS_WOCAW_DWAM.SNOOP_MISS",
        "MSWIndex": "0x1a6,0x1a7",
        "MSWVawue": "0x204000008",
        "SampweAftewVawue": "100003",
        "UMask": "0x1"
    },
    {
        "BwiefDescwiption": "Counts wwitebacks (modified to excwusive)",
        "EventCode": "0xB7, 0xBB",
        "EventName": "OFFCOWE_WESPONSE.COWEWB.W3_MISS_WOCAW_DWAM.SNOOP_NONE",
        "MSWIndex": "0x1a6,0x1a7",
        "MSWVawue": "0x84000008",
        "SampweAftewVawue": "100003",
        "UMask": "0x1"
    },
    {
        "BwiefDescwiption": "Counts wwitebacks (modified to excwusive)",
        "EventCode": "0xB7, 0xBB",
        "EventName": "OFFCOWE_WESPONSE.COWEWB.W3_MISS_WOCAW_DWAM.SNOOP_NON_DWAM",
        "MSWIndex": "0x1a6,0x1a7",
        "MSWVawue": "0x2004000008",
        "SampweAftewVawue": "100003",
        "UMask": "0x1"
    },
    {
        "BwiefDescwiption": "Counts wwitebacks (modified to excwusive)",
        "EventCode": "0xB7, 0xBB",
        "EventName": "OFFCOWE_WESPONSE.COWEWB.W3_MISS_WOCAW_DWAM.SNOOP_NOT_NEEDED",
        "MSWIndex": "0x1a6,0x1a7",
        "MSWVawue": "0x104000008",
        "SampweAftewVawue": "100003",
        "UMask": "0x1"
    },
    {
        "BwiefDescwiption": "Counts wwitebacks (modified to excwusive)",
        "EventCode": "0xB7, 0xBB",
        "EventName": "OFFCOWE_WESPONSE.COWEWB.SUPPWIEW_NONE.SNOOP_NON_DWAM",
        "MSWIndex": "0x1a6,0x1a7",
        "MSWVawue": "0x2000020008",
        "SampweAftewVawue": "100003",
        "UMask": "0x1"
    },
    {
        "BwiefDescwiption": "Counts aww demand code weads",
        "EventCode": "0xB7, 0xBB",
        "EventName": "OFFCOWE_WESPONSE.DEMAND_CODE_WD.W3_HIT.SNOOP_NON_DWAM",
        "MSWIndex": "0x1a6,0x1a7",
        "MSWVawue": "0x20003C0004",
        "SampweAftewVawue": "100003",
        "UMask": "0x1"
    },
    {
        "BwiefDescwiption": "Counts aww demand code weads",
        "EventCode": "0xB7, 0xBB",
        "EventName": "OFFCOWE_WESPONSE.DEMAND_CODE_WD.W3_MISS.SNOOP_HIT_NO_FWD",
        "MSWIndex": "0x1a6,0x1a7",
        "MSWVawue": "0x43C000004",
        "SampweAftewVawue": "100003",
        "UMask": "0x1"
    },
    {
        "BwiefDescwiption": "Counts aww demand code weads",
        "EventCode": "0xB7, 0xBB",
        "EventName": "OFFCOWE_WESPONSE.DEMAND_CODE_WD.W3_MISS.SNOOP_MISS",
        "MSWIndex": "0x1a6,0x1a7",
        "MSWVawue": "0x23C000004",
        "SampweAftewVawue": "100003",
        "UMask": "0x1"
    },
    {
        "BwiefDescwiption": "Counts aww demand code weads",
        "EventCode": "0xB7, 0xBB",
        "EventName": "OFFCOWE_WESPONSE.DEMAND_CODE_WD.W3_MISS.SNOOP_NONE",
        "MSWIndex": "0x1a6,0x1a7",
        "MSWVawue": "0xBC000004",
        "SampweAftewVawue": "100003",
        "UMask": "0x1"
    },
    {
        "BwiefDescwiption": "Counts aww demand code weads",
        "EventCode": "0xB7, 0xBB",
        "EventName": "OFFCOWE_WESPONSE.DEMAND_CODE_WD.W3_MISS.SNOOP_NOT_NEEDED",
        "MSWIndex": "0x1a6,0x1a7",
        "MSWVawue": "0x13C000004",
        "SampweAftewVawue": "100003",
        "UMask": "0x1"
    },
    {
        "BwiefDescwiption": "Counts aww demand code weads",
        "EventCode": "0xB7, 0xBB",
        "EventName": "OFFCOWE_WESPONSE.DEMAND_CODE_WD.W3_MISS_WOCAW_DWAM.ANY_SNOOP",
        "MSWIndex": "0x1a6,0x1a7",
        "MSWVawue": "0x3F84000004",
        "SampweAftewVawue": "100003",
        "UMask": "0x1"
    },
    {
        "BwiefDescwiption": "Counts aww demand code weads",
        "EventCode": "0xB7, 0xBB",
        "EventName": "OFFCOWE_WESPONSE.DEMAND_CODE_WD.W3_MISS_WOCAW_DWAM.SNOOP_HITM",
        "MSWIndex": "0x1a6,0x1a7",
        "MSWVawue": "0x1004000004",
        "SampweAftewVawue": "100003",
        "UMask": "0x1"
    },
    {
        "BwiefDescwiption": "Counts aww demand code weads",
        "EventCode": "0xB7, 0xBB",
        "EventName": "OFFCOWE_WESPONSE.DEMAND_CODE_WD.W3_MISS_WOCAW_DWAM.SNOOP_HIT_NO_FWD",
        "MSWIndex": "0x1a6,0x1a7",
        "MSWVawue": "0x404000004",
        "SampweAftewVawue": "100003",
        "UMask": "0x1"
    },
    {
        "BwiefDescwiption": "Counts aww demand code weads",
        "EventCode": "0xB7, 0xBB",
        "EventName": "OFFCOWE_WESPONSE.DEMAND_CODE_WD.W3_MISS_WOCAW_DWAM.SNOOP_MISS",
        "MSWIndex": "0x1a6,0x1a7",
        "MSWVawue": "0x204000004",
        "SampweAftewVawue": "100003",
        "UMask": "0x1"
    },
    {
        "BwiefDescwiption": "Counts aww demand code weads",
        "EventCode": "0xB7, 0xBB",
        "EventName": "OFFCOWE_WESPONSE.DEMAND_CODE_WD.W3_MISS_WOCAW_DWAM.SNOOP_NONE",
        "MSWIndex": "0x1a6,0x1a7",
        "MSWVawue": "0x84000004",
        "SampweAftewVawue": "100003",
        "UMask": "0x1"
    },
    {
        "BwiefDescwiption": "Counts aww demand code weads",
        "EventCode": "0xB7, 0xBB",
        "EventName": "OFFCOWE_WESPONSE.DEMAND_CODE_WD.W3_MISS_WOCAW_DWAM.SNOOP_NON_DWAM",
        "MSWIndex": "0x1a6,0x1a7",
        "MSWVawue": "0x2004000004",
        "SampweAftewVawue": "100003",
        "UMask": "0x1"
    },
    {
        "BwiefDescwiption": "Counts aww demand code weads",
        "EventCode": "0xB7, 0xBB",
        "EventName": "OFFCOWE_WESPONSE.DEMAND_CODE_WD.W3_MISS_WOCAW_DWAM.SNOOP_NOT_NEEDED",
        "MSWIndex": "0x1a6,0x1a7",
        "MSWVawue": "0x104000004",
        "SampweAftewVawue": "100003",
        "UMask": "0x1"
    },
    {
        "BwiefDescwiption": "Counts aww demand code weads",
        "EventCode": "0xB7, 0xBB",
        "EventName": "OFFCOWE_WESPONSE.DEMAND_CODE_WD.SUPPWIEW_NONE.SNOOP_NON_DWAM",
        "MSWIndex": "0x1a6,0x1a7",
        "MSWVawue": "0x2000020004",
        "SampweAftewVawue": "100003",
        "UMask": "0x1"
    },
    {
        "BwiefDescwiption": "Counts demand data weads",
        "EventCode": "0xB7, 0xBB",
        "EventName": "OFFCOWE_WESPONSE.DEMAND_DATA_WD.W3_HIT.SNOOP_NON_DWAM",
        "MSWIndex": "0x1a6,0x1a7",
        "MSWVawue": "0x20003C0001",
        "SampweAftewVawue": "100003",
        "UMask": "0x1"
    },
    {
        "BwiefDescwiption": "Counts demand data weads",
        "EventCode": "0xB7, 0xBB",
        "EventName": "OFFCOWE_WESPONSE.DEMAND_DATA_WD.W3_MISS.SNOOP_HIT_NO_FWD",
        "MSWIndex": "0x1a6,0x1a7",
        "MSWVawue": "0x43C000001",
        "SampweAftewVawue": "100003",
        "UMask": "0x1"
    },
    {
        "BwiefDescwiption": "Counts demand data weads",
        "EventCode": "0xB7, 0xBB",
        "EventName": "OFFCOWE_WESPONSE.DEMAND_DATA_WD.W3_MISS.SNOOP_MISS",
        "MSWIndex": "0x1a6,0x1a7",
        "MSWVawue": "0x23C000001",
        "SampweAftewVawue": "100003",
        "UMask": "0x1"
    },
    {
        "BwiefDescwiption": "Counts demand data weads",
        "EventCode": "0xB7, 0xBB",
        "EventName": "OFFCOWE_WESPONSE.DEMAND_DATA_WD.W3_MISS.SNOOP_NONE",
        "MSWIndex": "0x1a6,0x1a7",
        "MSWVawue": "0xBC000001",
        "SampweAftewVawue": "100003",
        "UMask": "0x1"
    },
    {
        "BwiefDescwiption": "Counts demand data weads",
        "EventCode": "0xB7, 0xBB",
        "EventName": "OFFCOWE_WESPONSE.DEMAND_DATA_WD.W3_MISS.SNOOP_NOT_NEEDED",
        "MSWIndex": "0x1a6,0x1a7",
        "MSWVawue": "0x13C000001",
        "SampweAftewVawue": "100003",
        "UMask": "0x1"
    },
    {
        "BwiefDescwiption": "Counts demand data weads",
        "EventCode": "0xB7, 0xBB",
        "EventName": "OFFCOWE_WESPONSE.DEMAND_DATA_WD.W3_MISS_WOCAW_DWAM.ANY_SNOOP",
        "MSWIndex": "0x1a6,0x1a7",
        "MSWVawue": "0x3F84000001",
        "SampweAftewVawue": "100003",
        "UMask": "0x1"
    },
    {
        "BwiefDescwiption": "Counts demand data weads",
        "EventCode": "0xB7, 0xBB",
        "EventName": "OFFCOWE_WESPONSE.DEMAND_DATA_WD.W3_MISS_WOCAW_DWAM.SNOOP_HITM",
        "MSWIndex": "0x1a6,0x1a7",
        "MSWVawue": "0x1004000001",
        "SampweAftewVawue": "100003",
        "UMask": "0x1"
    },
    {
        "BwiefDescwiption": "Counts demand data weads",
        "EventCode": "0xB7, 0xBB",
        "EventName": "OFFCOWE_WESPONSE.DEMAND_DATA_WD.W3_MISS_WOCAW_DWAM.SNOOP_HIT_NO_FWD",
        "MSWIndex": "0x1a6,0x1a7",
        "MSWVawue": "0x404000001",
        "SampweAftewVawue": "100003",
        "UMask": "0x1"
    },
    {
        "BwiefDescwiption": "Counts demand data weads",
        "EventCode": "0xB7, 0xBB",
        "EventName": "OFFCOWE_WESPONSE.DEMAND_DATA_WD.W3_MISS_WOCAW_DWAM.SNOOP_MISS",
        "MSWIndex": "0x1a6,0x1a7",
        "MSWVawue": "0x204000001",
        "SampweAftewVawue": "100003",
        "UMask": "0x1"
    },
    {
        "BwiefDescwiption": "Counts demand data weads",
        "EventCode": "0xB7, 0xBB",
        "EventName": "OFFCOWE_WESPONSE.DEMAND_DATA_WD.W3_MISS_WOCAW_DWAM.SNOOP_NONE",
        "MSWIndex": "0x1a6,0x1a7",
        "MSWVawue": "0x84000001",
        "SampweAftewVawue": "100003",
        "UMask": "0x1"
    },
    {
        "BwiefDescwiption": "Counts demand data weads",
        "EventCode": "0xB7, 0xBB",
        "EventName": "OFFCOWE_WESPONSE.DEMAND_DATA_WD.W3_MISS_WOCAW_DWAM.SNOOP_NON_DWAM",
        "MSWIndex": "0x1a6,0x1a7",
        "MSWVawue": "0x2004000001",
        "SampweAftewVawue": "100003",
        "UMask": "0x1"
    },
    {
        "BwiefDescwiption": "Counts demand data weads",
        "EventCode": "0xB7, 0xBB",
        "EventName": "OFFCOWE_WESPONSE.DEMAND_DATA_WD.W3_MISS_WOCAW_DWAM.SNOOP_NOT_NEEDED",
        "MSWIndex": "0x1a6,0x1a7",
        "MSWVawue": "0x104000001",
        "SampweAftewVawue": "100003",
        "UMask": "0x1"
    },
    {
        "BwiefDescwiption": "Counts demand data weads",
        "EventCode": "0xB7, 0xBB",
        "EventName": "OFFCOWE_WESPONSE.DEMAND_DATA_WD.SUPPWIEW_NONE.SNOOP_NON_DWAM",
        "MSWIndex": "0x1a6,0x1a7",
        "MSWVawue": "0x2000020001",
        "SampweAftewVawue": "100003",
        "UMask": "0x1"
    },
    {
        "BwiefDescwiption": "Counts aww demand data wwites (WFOs)",
        "EventCode": "0xB7, 0xBB",
        "EventName": "OFFCOWE_WESPONSE.DEMAND_WFO.W3_HIT.SNOOP_NON_DWAM",
        "MSWIndex": "0x1a6,0x1a7",
        "MSWVawue": "0x20003C0002",
        "SampweAftewVawue": "100003",
        "UMask": "0x1"
    },
    {
        "BwiefDescwiption": "Counts aww demand data wwites (WFOs)",
        "EventCode": "0xB7, 0xBB",
        "EventName": "OFFCOWE_WESPONSE.DEMAND_WFO.W3_MISS.SNOOP_HIT_NO_FWD",
        "MSWIndex": "0x1a6,0x1a7",
        "MSWVawue": "0x43C000002",
        "SampweAftewVawue": "100003",
        "UMask": "0x1"
    },
    {
        "BwiefDescwiption": "Counts aww demand data wwites (WFOs)",
        "EventCode": "0xB7, 0xBB",
        "EventName": "OFFCOWE_WESPONSE.DEMAND_WFO.W3_MISS.SNOOP_MISS",
        "MSWIndex": "0x1a6,0x1a7",
        "MSWVawue": "0x23C000002",
        "SampweAftewVawue": "100003",
        "UMask": "0x1"
    },
    {
        "BwiefDescwiption": "Counts aww demand data wwites (WFOs)",
        "EventCode": "0xB7, 0xBB",
        "EventName": "OFFCOWE_WESPONSE.DEMAND_WFO.W3_MISS.SNOOP_NONE",
        "MSWIndex": "0x1a6,0x1a7",
        "MSWVawue": "0xBC000002",
        "SampweAftewVawue": "100003",
        "UMask": "0x1"
    },
    {
        "BwiefDescwiption": "Counts aww demand data wwites (WFOs)",
        "EventCode": "0xB7, 0xBB",
        "EventName": "OFFCOWE_WESPONSE.DEMAND_WFO.W3_MISS.SNOOP_NOT_NEEDED",
        "MSWIndex": "0x1a6,0x1a7",
        "MSWVawue": "0x13C000002",
        "SampweAftewVawue": "100003",
        "UMask": "0x1"
    },
    {
        "BwiefDescwiption": "Counts aww demand data wwites (WFOs)",
        "EventCode": "0xB7, 0xBB",
        "EventName": "OFFCOWE_WESPONSE.DEMAND_WFO.W3_MISS_WOCAW_DWAM.ANY_SNOOP",
        "MSWIndex": "0x1a6,0x1a7",
        "MSWVawue": "0x3F84000002",
        "SampweAftewVawue": "100003",
        "UMask": "0x1"
    },
    {
        "BwiefDescwiption": "Counts any othew wequests",
        "EventCode": "0xB7, 0xBB",
        "EventName": "OFFCOWE_WESPONSE.OTHEW.W3_HIT.SNOOP_NON_DWAM",
        "MSWIndex": "0x1a6,0x1a7",
        "MSWVawue": "0x20003C8000",
        "SampweAftewVawue": "100003",
        "UMask": "0x1"
    },
    {
        "BwiefDescwiption": "Counts any othew wequests",
        "EventCode": "0xB7, 0xBB",
        "EventName": "OFFCOWE_WESPONSE.OTHEW.W3_MISS.SNOOP_HIT_NO_FWD",
        "MSWIndex": "0x1a6,0x1a7",
        "MSWVawue": "0x43C008000",
        "SampweAftewVawue": "100003",
        "UMask": "0x1"
    },
    {
        "BwiefDescwiption": "Counts any othew wequests",
        "EventCode": "0xB7, 0xBB",
        "EventName": "OFFCOWE_WESPONSE.OTHEW.W3_MISS.SNOOP_MISS",
        "MSWIndex": "0x1a6,0x1a7",
        "MSWVawue": "0x23C008000",
        "SampweAftewVawue": "100003",
        "UMask": "0x1"
    },
    {
        "BwiefDescwiption": "Counts any othew wequests",
        "EventCode": "0xB7, 0xBB",
        "EventName": "OFFCOWE_WESPONSE.OTHEW.W3_MISS.SNOOP_NONE",
        "MSWIndex": "0x1a6,0x1a7",
        "MSWVawue": "0xBC008000",
        "SampweAftewVawue": "100003",
        "UMask": "0x1"
    },
    {
        "BwiefDescwiption": "Counts any othew wequests",
        "EventCode": "0xB7, 0xBB",
        "EventName": "OFFCOWE_WESPONSE.OTHEW.W3_MISS.SNOOP_NOT_NEEDED",
        "MSWIndex": "0x1a6,0x1a7",
        "MSWVawue": "0x13C008000",
        "SampweAftewVawue": "100003",
        "UMask": "0x1"
    },
    {
        "BwiefDescwiption": "Counts any othew wequests",
        "EventCode": "0xB7, 0xBB",
        "EventName": "OFFCOWE_WESPONSE.OTHEW.W3_MISS_WOCAW_DWAM.ANY_SNOOP",
        "MSWIndex": "0x1a6,0x1a7",
        "MSWVawue": "0x3F84008000",
        "SampweAftewVawue": "100003",
        "UMask": "0x1"
    },
    {
        "BwiefDescwiption": "Counts any othew wequests",
        "EventCode": "0xB7, 0xBB",
        "EventName": "OFFCOWE_WESPONSE.OTHEW.W3_MISS_WOCAW_DWAM.SNOOP_HITM",
        "MSWIndex": "0x1a6,0x1a7",
        "MSWVawue": "0x1004008000",
        "SampweAftewVawue": "100003",
        "UMask": "0x1"
    },
    {
        "BwiefDescwiption": "Counts any othew wequests",
        "EventCode": "0xB7, 0xBB",
        "EventName": "OFFCOWE_WESPONSE.OTHEW.W3_MISS_WOCAW_DWAM.SNOOP_HIT_NO_FWD",
        "MSWIndex": "0x1a6,0x1a7",
        "MSWVawue": "0x404008000",
        "SampweAftewVawue": "100003",
        "UMask": "0x1"
    },
    {
        "BwiefDescwiption": "Counts any othew wequests",
        "EventCode": "0xB7, 0xBB",
        "EventName": "OFFCOWE_WESPONSE.OTHEW.W3_MISS_WOCAW_DWAM.SNOOP_MISS",
        "MSWIndex": "0x1a6,0x1a7",
        "MSWVawue": "0x204008000",
        "SampweAftewVawue": "100003",
        "UMask": "0x1"
    },
    {
        "BwiefDescwiption": "Counts any othew wequests",
        "EventCode": "0xB7, 0xBB",
        "EventName": "OFFCOWE_WESPONSE.OTHEW.W3_MISS_WOCAW_DWAM.SNOOP_NONE",
        "MSWIndex": "0x1a6,0x1a7",
        "MSWVawue": "0x84008000",
        "SampweAftewVawue": "100003",
        "UMask": "0x1"
    },
    {
        "BwiefDescwiption": "Counts any othew wequests",
        "EventCode": "0xB7, 0xBB",
        "EventName": "OFFCOWE_WESPONSE.OTHEW.W3_MISS_WOCAW_DWAM.SNOOP_NON_DWAM",
        "MSWIndex": "0x1a6,0x1a7",
        "MSWVawue": "0x2004008000",
        "SampweAftewVawue": "100003",
        "UMask": "0x1"
    },
    {
        "BwiefDescwiption": "Counts any othew wequests",
        "EventCode": "0xB7, 0xBB",
        "EventName": "OFFCOWE_WESPONSE.OTHEW.W3_MISS_WOCAW_DWAM.SNOOP_NOT_NEEDED",
        "MSWIndex": "0x1a6,0x1a7",
        "MSWVawue": "0x104008000",
        "SampweAftewVawue": "100003",
        "UMask": "0x1"
    },
    {
        "BwiefDescwiption": "Counts any othew wequests",
        "EventCode": "0xB7, 0xBB",
        "EventName": "OFFCOWE_WESPONSE.OTHEW.SUPPWIEW_NONE.SNOOP_NON_DWAM",
        "MSWIndex": "0x1a6,0x1a7",
        "MSWVawue": "0x2000028000",
        "SampweAftewVawue": "100003",
        "UMask": "0x1"
    },
    {
        "BwiefDescwiption": "Counts aww pwefetch (that bwing data to WWC onwy) code weads",
        "EventCode": "0xB7, 0xBB",
        "EventName": "OFFCOWE_WESPONSE.PF_W2_CODE_WD.W3_HIT.SNOOP_NON_DWAM",
        "MSWIndex": "0x1a6,0x1a7",
        "MSWVawue": "0x20003C0040",
        "SampweAftewVawue": "100003",
        "UMask": "0x1"
    },
    {
        "BwiefDescwiption": "Counts aww pwefetch (that bwing data to WWC onwy) code weads",
        "EventCode": "0xB7, 0xBB",
        "EventName": "OFFCOWE_WESPONSE.PF_W2_CODE_WD.W3_MISS.SNOOP_HIT_NO_FWD",
        "MSWIndex": "0x1a6,0x1a7",
        "MSWVawue": "0x43C000040",
        "SampweAftewVawue": "100003",
        "UMask": "0x1"
    },
    {
        "BwiefDescwiption": "Counts aww pwefetch (that bwing data to WWC onwy) code weads",
        "EventCode": "0xB7, 0xBB",
        "EventName": "OFFCOWE_WESPONSE.PF_W2_CODE_WD.W3_MISS.SNOOP_MISS",
        "MSWIndex": "0x1a6,0x1a7",
        "MSWVawue": "0x23C000040",
        "SampweAftewVawue": "100003",
        "UMask": "0x1"
    },
    {
        "BwiefDescwiption": "Counts aww pwefetch (that bwing data to WWC onwy) code weads",
        "EventCode": "0xB7, 0xBB",
        "EventName": "OFFCOWE_WESPONSE.PF_W2_CODE_WD.W3_MISS.SNOOP_NONE",
        "MSWIndex": "0x1a6,0x1a7",
        "MSWVawue": "0xBC000040",
        "SampweAftewVawue": "100003",
        "UMask": "0x1"
    },
    {
        "BwiefDescwiption": "Counts aww pwefetch (that bwing data to WWC onwy) code weads",
        "EventCode": "0xB7, 0xBB",
        "EventName": "OFFCOWE_WESPONSE.PF_W2_CODE_WD.W3_MISS.SNOOP_NOT_NEEDED",
        "MSWIndex": "0x1a6,0x1a7",
        "MSWVawue": "0x13C000040",
        "SampweAftewVawue": "100003",
        "UMask": "0x1"
    },
    {
        "BwiefDescwiption": "Counts aww pwefetch (that bwing data to WWC onwy) code weads",
        "EventCode": "0xB7, 0xBB",
        "EventName": "OFFCOWE_WESPONSE.PF_W2_CODE_WD.W3_MISS_WOCAW_DWAM.ANY_SNOOP",
        "MSWIndex": "0x1a6,0x1a7",
        "MSWVawue": "0x3F84000040",
        "SampweAftewVawue": "100003",
        "UMask": "0x1"
    },
    {
        "BwiefDescwiption": "Counts aww pwefetch (that bwing data to WWC onwy) code weads",
        "EventCode": "0xB7, 0xBB",
        "EventName": "OFFCOWE_WESPONSE.PF_W2_CODE_WD.W3_MISS_WOCAW_DWAM.SNOOP_HITM",
        "MSWIndex": "0x1a6,0x1a7",
        "MSWVawue": "0x1004000040",
        "SampweAftewVawue": "100003",
        "UMask": "0x1"
    },
    {
        "BwiefDescwiption": "Counts aww pwefetch (that bwing data to WWC onwy) code weads",
        "EventCode": "0xB7, 0xBB",
        "EventName": "OFFCOWE_WESPONSE.PF_W2_CODE_WD.W3_MISS_WOCAW_DWAM.SNOOP_HIT_NO_FWD",
        "MSWIndex": "0x1a6,0x1a7",
        "MSWVawue": "0x404000040",
        "SampweAftewVawue": "100003",
        "UMask": "0x1"
    },
    {
        "BwiefDescwiption": "Counts aww pwefetch (that bwing data to WWC onwy) code weads",
        "EventCode": "0xB7, 0xBB",
        "EventName": "OFFCOWE_WESPONSE.PF_W2_CODE_WD.W3_MISS_WOCAW_DWAM.SNOOP_MISS",
        "MSWIndex": "0x1a6,0x1a7",
        "MSWVawue": "0x204000040",
        "SampweAftewVawue": "100003",
        "UMask": "0x1"
    },
    {
        "BwiefDescwiption": "Counts aww pwefetch (that bwing data to WWC onwy) code weads",
        "EventCode": "0xB7, 0xBB",
        "EventName": "OFFCOWE_WESPONSE.PF_W2_CODE_WD.W3_MISS_WOCAW_DWAM.SNOOP_NONE",
        "MSWIndex": "0x1a6,0x1a7",
        "MSWVawue": "0x84000040",
        "SampweAftewVawue": "100003",
        "UMask": "0x1"
    },
    {
        "BwiefDescwiption": "Counts aww pwefetch (that bwing data to WWC onwy) code weads",
        "EventCode": "0xB7, 0xBB",
        "EventName": "OFFCOWE_WESPONSE.PF_W2_CODE_WD.W3_MISS_WOCAW_DWAM.SNOOP_NON_DWAM",
        "MSWIndex": "0x1a6,0x1a7",
        "MSWVawue": "0x2004000040",
        "SampweAftewVawue": "100003",
        "UMask": "0x1"
    },
    {
        "BwiefDescwiption": "Counts aww pwefetch (that bwing data to WWC onwy) code weads",
        "EventCode": "0xB7, 0xBB",
        "EventName": "OFFCOWE_WESPONSE.PF_W2_CODE_WD.W3_MISS_WOCAW_DWAM.SNOOP_NOT_NEEDED",
        "MSWIndex": "0x1a6,0x1a7",
        "MSWVawue": "0x104000040",
        "SampweAftewVawue": "100003",
        "UMask": "0x1"
    },
    {
        "BwiefDescwiption": "Counts aww pwefetch (that bwing data to WWC onwy) code weads",
        "EventCode": "0xB7, 0xBB",
        "EventName": "OFFCOWE_WESPONSE.PF_W2_CODE_WD.SUPPWIEW_NONE.SNOOP_NON_DWAM",
        "MSWIndex": "0x1a6,0x1a7",
        "MSWVawue": "0x2000020040",
        "SampweAftewVawue": "100003",
        "UMask": "0x1"
    },
    {
        "BwiefDescwiption": "Counts pwefetch (that bwing data to W2) data weads",
        "EventCode": "0xB7, 0xBB",
        "EventName": "OFFCOWE_WESPONSE.PF_W2_DATA_WD.W3_HIT.SNOOP_NON_DWAM",
        "MSWIndex": "0x1a6,0x1a7",
        "MSWVawue": "0x20003C0010",
        "SampweAftewVawue": "100003",
        "UMask": "0x1"
    },
    {
        "BwiefDescwiption": "Counts pwefetch (that bwing data to W2) data weads",
        "EventCode": "0xB7, 0xBB",
        "EventName": "OFFCOWE_WESPONSE.PF_W2_DATA_WD.W3_MISS.SNOOP_HIT_NO_FWD",
        "MSWIndex": "0x1a6,0x1a7",
        "MSWVawue": "0x43C000010",
        "SampweAftewVawue": "100003",
        "UMask": "0x1"
    },
    {
        "BwiefDescwiption": "Counts pwefetch (that bwing data to W2) data weads",
        "EventCode": "0xB7, 0xBB",
        "EventName": "OFFCOWE_WESPONSE.PF_W2_DATA_WD.W3_MISS.SNOOP_MISS",
        "MSWIndex": "0x1a6,0x1a7",
        "MSWVawue": "0x23C000010",
        "SampweAftewVawue": "100003",
        "UMask": "0x1"
    },
    {
        "BwiefDescwiption": "Counts pwefetch (that bwing data to W2) data weads",
        "EventCode": "0xB7, 0xBB",
        "EventName": "OFFCOWE_WESPONSE.PF_W2_DATA_WD.W3_MISS.SNOOP_NONE",
        "MSWIndex": "0x1a6,0x1a7",
        "MSWVawue": "0xBC000010",
        "SampweAftewVawue": "100003",
        "UMask": "0x1"
    },
    {
        "BwiefDescwiption": "Counts pwefetch (that bwing data to W2) data weads",
        "EventCode": "0xB7, 0xBB",
        "EventName": "OFFCOWE_WESPONSE.PF_W2_DATA_WD.W3_MISS.SNOOP_NOT_NEEDED",
        "MSWIndex": "0x1a6,0x1a7",
        "MSWVawue": "0x13C000010",
        "SampweAftewVawue": "100003",
        "UMask": "0x1"
    },
    {
        "BwiefDescwiption": "Counts pwefetch (that bwing data to W2) data weads",
        "EventCode": "0xB7, 0xBB",
        "EventName": "OFFCOWE_WESPONSE.PF_W2_DATA_WD.W3_MISS_WOCAW_DWAM.ANY_SNOOP",
        "MSWIndex": "0x1a6,0x1a7",
        "MSWVawue": "0x3F84000010",
        "SampweAftewVawue": "100003",
        "UMask": "0x1"
    },
    {
        "BwiefDescwiption": "Counts pwefetch (that bwing data to W2) data weads",
        "EventCode": "0xB7, 0xBB",
        "EventName": "OFFCOWE_WESPONSE.PF_W2_DATA_WD.W3_MISS_WOCAW_DWAM.SNOOP_HITM",
        "MSWIndex": "0x1a6,0x1a7",
        "MSWVawue": "0x1004000010",
        "SampweAftewVawue": "100003",
        "UMask": "0x1"
    },
    {
        "BwiefDescwiption": "Counts pwefetch (that bwing data to W2) data weads",
        "EventCode": "0xB7, 0xBB",
        "EventName": "OFFCOWE_WESPONSE.PF_W2_DATA_WD.W3_MISS_WOCAW_DWAM.SNOOP_HIT_NO_FWD",
        "MSWIndex": "0x1a6,0x1a7",
        "MSWVawue": "0x404000010",
        "SampweAftewVawue": "100003",
        "UMask": "0x1"
    },
    {
        "BwiefDescwiption": "Counts pwefetch (that bwing data to W2) data weads",
        "EventCode": "0xB7, 0xBB",
        "EventName": "OFFCOWE_WESPONSE.PF_W2_DATA_WD.W3_MISS_WOCAW_DWAM.SNOOP_MISS",
        "MSWIndex": "0x1a6,0x1a7",
        "MSWVawue": "0x204000010",
        "SampweAftewVawue": "100003",
        "UMask": "0x1"
    },
    {
        "BwiefDescwiption": "Counts pwefetch (that bwing data to W2) data weads",
        "EventCode": "0xB7, 0xBB",
        "EventName": "OFFCOWE_WESPONSE.PF_W2_DATA_WD.W3_MISS_WOCAW_DWAM.SNOOP_NONE",
        "MSWIndex": "0x1a6,0x1a7",
        "MSWVawue": "0x84000010",
        "SampweAftewVawue": "100003",
        "UMask": "0x1"
    },
    {
        "BwiefDescwiption": "Counts pwefetch (that bwing data to W2) data weads",
        "EventCode": "0xB7, 0xBB",
        "EventName": "OFFCOWE_WESPONSE.PF_W2_DATA_WD.W3_MISS_WOCAW_DWAM.SNOOP_NON_DWAM",
        "MSWIndex": "0x1a6,0x1a7",
        "MSWVawue": "0x2004000010",
        "SampweAftewVawue": "100003",
        "UMask": "0x1"
    },
    {
        "BwiefDescwiption": "Counts pwefetch (that bwing data to W2) data weads",
        "EventCode": "0xB7, 0xBB",
        "EventName": "OFFCOWE_WESPONSE.PF_W2_DATA_WD.W3_MISS_WOCAW_DWAM.SNOOP_NOT_NEEDED",
        "MSWIndex": "0x1a6,0x1a7",
        "MSWVawue": "0x104000010",
        "SampweAftewVawue": "100003",
        "UMask": "0x1"
    },
    {
        "BwiefDescwiption": "Counts pwefetch (that bwing data to W2) data weads",
        "EventCode": "0xB7, 0xBB",
        "EventName": "OFFCOWE_WESPONSE.PF_W2_DATA_WD.SUPPWIEW_NONE.SNOOP_NON_DWAM",
        "MSWIndex": "0x1a6,0x1a7",
        "MSWVawue": "0x2000020010",
        "SampweAftewVawue": "100003",
        "UMask": "0x1"
    },
    {
        "BwiefDescwiption": "Counts aww pwefetch (that bwing data to W2) WFOs",
        "EventCode": "0xB7, 0xBB",
        "EventName": "OFFCOWE_WESPONSE.PF_W2_WFO.W3_HIT.SNOOP_NON_DWAM",
        "MSWIndex": "0x1a6,0x1a7",
        "MSWVawue": "0x20003C0020",
        "SampweAftewVawue": "100003",
        "UMask": "0x1"
    },
    {
        "BwiefDescwiption": "Counts aww pwefetch (that bwing data to W2) WFOs",
        "EventCode": "0xB7, 0xBB",
        "EventName": "OFFCOWE_WESPONSE.PF_W2_WFO.W3_MISS.SNOOP_HIT_NO_FWD",
        "MSWIndex": "0x1a6,0x1a7",
        "MSWVawue": "0x43C000020",
        "SampweAftewVawue": "100003",
        "UMask": "0x1"
    },
    {
        "BwiefDescwiption": "Counts aww pwefetch (that bwing data to W2) WFOs",
        "EventCode": "0xB7, 0xBB",
        "EventName": "OFFCOWE_WESPONSE.PF_W2_WFO.W3_MISS.SNOOP_MISS",
        "MSWIndex": "0x1a6,0x1a7",
        "MSWVawue": "0x23C000020",
        "SampweAftewVawue": "100003",
        "UMask": "0x1"
    },
    {
        "BwiefDescwiption": "Counts aww pwefetch (that bwing data to W2) WFOs",
        "EventCode": "0xB7, 0xBB",
        "EventName": "OFFCOWE_WESPONSE.PF_W2_WFO.W3_MISS.SNOOP_NONE",
        "MSWIndex": "0x1a6,0x1a7",
        "MSWVawue": "0xBC000020",
        "SampweAftewVawue": "100003",
        "UMask": "0x1"
    },
    {
        "BwiefDescwiption": "Counts aww pwefetch (that bwing data to W2) WFOs",
        "EventCode": "0xB7, 0xBB",
        "EventName": "OFFCOWE_WESPONSE.PF_W2_WFO.W3_MISS.SNOOP_NOT_NEEDED",
        "MSWIndex": "0x1a6,0x1a7",
        "MSWVawue": "0x13C000020",
        "SampweAftewVawue": "100003",
        "UMask": "0x1"
    },
    {
        "BwiefDescwiption": "Counts aww pwefetch (that bwing data to W2) WFOs",
        "EventCode": "0xB7, 0xBB",
        "EventName": "OFFCOWE_WESPONSE.PF_W2_WFO.W3_MISS_WOCAW_DWAM.ANY_SNOOP",
        "MSWIndex": "0x1a6,0x1a7",
        "MSWVawue": "0x3F84000020",
        "SampweAftewVawue": "100003",
        "UMask": "0x1"
    },
    {
        "BwiefDescwiption": "Counts aww pwefetch (that bwing data to W2) WFOs",
        "EventCode": "0xB7, 0xBB",
        "EventName": "OFFCOWE_WESPONSE.PF_W2_WFO.W3_MISS_WOCAW_DWAM.SNOOP_HITM",
        "MSWIndex": "0x1a6,0x1a7",
        "MSWVawue": "0x1004000020",
        "SampweAftewVawue": "100003",
        "UMask": "0x1"
    },
    {
        "BwiefDescwiption": "Counts aww pwefetch (that bwing data to W2) WFOs",
        "EventCode": "0xB7, 0xBB",
        "EventName": "OFFCOWE_WESPONSE.PF_W2_WFO.W3_MISS_WOCAW_DWAM.SNOOP_HIT_NO_FWD",
        "MSWIndex": "0x1a6,0x1a7",
        "MSWVawue": "0x404000020",
        "SampweAftewVawue": "100003",
        "UMask": "0x1"
    },
    {
        "BwiefDescwiption": "Counts aww pwefetch (that bwing data to W2) WFOs",
        "EventCode": "0xB7, 0xBB",
        "EventName": "OFFCOWE_WESPONSE.PF_W2_WFO.W3_MISS_WOCAW_DWAM.SNOOP_MISS",
        "MSWIndex": "0x1a6,0x1a7",
        "MSWVawue": "0x204000020",
        "SampweAftewVawue": "100003",
        "UMask": "0x1"
    },
    {
        "BwiefDescwiption": "Counts aww pwefetch (that bwing data to W2) WFOs",
        "EventCode": "0xB7, 0xBB",
        "EventName": "OFFCOWE_WESPONSE.PF_W2_WFO.W3_MISS_WOCAW_DWAM.SNOOP_NONE",
        "MSWIndex": "0x1a6,0x1a7",
        "MSWVawue": "0x84000020",
        "SampweAftewVawue": "100003",
        "UMask": "0x1"
    },
    {
        "BwiefDescwiption": "Counts aww pwefetch (that bwing data to W2) WFOs",
        "EventCode": "0xB7, 0xBB",
        "EventName": "OFFCOWE_WESPONSE.PF_W2_WFO.W3_MISS_WOCAW_DWAM.SNOOP_NON_DWAM",
        "MSWIndex": "0x1a6,0x1a7",
        "MSWVawue": "0x2004000020",
        "SampweAftewVawue": "100003",
        "UMask": "0x1"
    },
    {
        "BwiefDescwiption": "Counts aww pwefetch (that bwing data to W2) WFOs",
        "EventCode": "0xB7, 0xBB",
        "EventName": "OFFCOWE_WESPONSE.PF_W2_WFO.W3_MISS_WOCAW_DWAM.SNOOP_NOT_NEEDED",
        "MSWIndex": "0x1a6,0x1a7",
        "MSWVawue": "0x104000020",
        "SampweAftewVawue": "100003",
        "UMask": "0x1"
    },
    {
        "BwiefDescwiption": "Counts aww pwefetch (that bwing data to W2) WFOs",
        "EventCode": "0xB7, 0xBB",
        "EventName": "OFFCOWE_WESPONSE.PF_W2_WFO.SUPPWIEW_NONE.SNOOP_NON_DWAM",
        "MSWIndex": "0x1a6,0x1a7",
        "MSWVawue": "0x2000020020",
        "SampweAftewVawue": "100003",
        "UMask": "0x1"
    },
    {
        "BwiefDescwiption": "Counts pwefetch (that bwing data to WWC onwy) code weads",
        "EventCode": "0xB7, 0xBB",
        "EventName": "OFFCOWE_WESPONSE.PF_W3_CODE_WD.W3_HIT.SNOOP_NON_DWAM",
        "MSWIndex": "0x1a6,0x1a7",
        "MSWVawue": "0x20003C0200",
        "SampweAftewVawue": "100003",
        "UMask": "0x1"
    },
    {
        "BwiefDescwiption": "Counts pwefetch (that bwing data to WWC onwy) code weads",
        "EventCode": "0xB7, 0xBB",
        "EventName": "OFFCOWE_WESPONSE.PF_W3_CODE_WD.W3_MISS.SNOOP_HIT_NO_FWD",
        "MSWIndex": "0x1a6,0x1a7",
        "MSWVawue": "0x43C000200",
        "SampweAftewVawue": "100003",
        "UMask": "0x1"
    },
    {
        "BwiefDescwiption": "Counts pwefetch (that bwing data to WWC onwy) code weads",
        "EventCode": "0xB7, 0xBB",
        "EventName": "OFFCOWE_WESPONSE.PF_W3_CODE_WD.W3_MISS.SNOOP_MISS",
        "MSWIndex": "0x1a6,0x1a7",
        "MSWVawue": "0x23C000200",
        "SampweAftewVawue": "100003",
        "UMask": "0x1"
    },
    {
        "BwiefDescwiption": "Counts pwefetch (that bwing data to WWC onwy) code weads",
        "EventCode": "0xB7, 0xBB",
        "EventName": "OFFCOWE_WESPONSE.PF_W3_CODE_WD.W3_MISS.SNOOP_NONE",
        "MSWIndex": "0x1a6,0x1a7",
        "MSWVawue": "0xBC000200",
        "SampweAftewVawue": "100003",
        "UMask": "0x1"
    },
    {
        "BwiefDescwiption": "Counts pwefetch (that bwing data to WWC onwy) code weads",
        "EventCode": "0xB7, 0xBB",
        "EventName": "OFFCOWE_WESPONSE.PF_W3_CODE_WD.W3_MISS.SNOOP_NOT_NEEDED",
        "MSWIndex": "0x1a6,0x1a7",
        "MSWVawue": "0x13C000200",
        "SampweAftewVawue": "100003",
        "UMask": "0x1"
    },
    {
        "BwiefDescwiption": "Counts pwefetch (that bwing data to WWC onwy) code weads",
        "EventCode": "0xB7, 0xBB",
        "EventName": "OFFCOWE_WESPONSE.PF_W3_CODE_WD.W3_MISS_WOCAW_DWAM.ANY_SNOOP",
        "MSWIndex": "0x1a6,0x1a7",
        "MSWVawue": "0x3F84000200",
        "SampweAftewVawue": "100003",
        "UMask": "0x1"
    },
    {
        "BwiefDescwiption": "Counts pwefetch (that bwing data to WWC onwy) code weads",
        "EventCode": "0xB7, 0xBB",
        "EventName": "OFFCOWE_WESPONSE.PF_W3_CODE_WD.W3_MISS_WOCAW_DWAM.SNOOP_HITM",
        "MSWIndex": "0x1a6,0x1a7",
        "MSWVawue": "0x1004000200",
        "SampweAftewVawue": "100003",
        "UMask": "0x1"
    },
    {
        "BwiefDescwiption": "Counts pwefetch (that bwing data to WWC onwy) code weads",
        "EventCode": "0xB7, 0xBB",
        "EventName": "OFFCOWE_WESPONSE.PF_W3_CODE_WD.W3_MISS_WOCAW_DWAM.SNOOP_HIT_NO_FWD",
        "MSWIndex": "0x1a6,0x1a7",
        "MSWVawue": "0x404000200",
        "SampweAftewVawue": "100003",
        "UMask": "0x1"
    },
    {
        "BwiefDescwiption": "Counts pwefetch (that bwing data to WWC onwy) code weads",
        "EventCode": "0xB7, 0xBB",
        "EventName": "OFFCOWE_WESPONSE.PF_W3_CODE_WD.W3_MISS_WOCAW_DWAM.SNOOP_MISS",
        "MSWIndex": "0x1a6,0x1a7",
        "MSWVawue": "0x204000200",
        "SampweAftewVawue": "100003",
        "UMask": "0x1"
    },
    {
        "BwiefDescwiption": "Counts pwefetch (that bwing data to WWC onwy) code weads",
        "EventCode": "0xB7, 0xBB",
        "EventName": "OFFCOWE_WESPONSE.PF_W3_CODE_WD.W3_MISS_WOCAW_DWAM.SNOOP_NONE",
        "MSWIndex": "0x1a6,0x1a7",
        "MSWVawue": "0x84000200",
        "SampweAftewVawue": "100003",
        "UMask": "0x1"
    },
    {
        "BwiefDescwiption": "Counts pwefetch (that bwing data to WWC onwy) code weads",
        "EventCode": "0xB7, 0xBB",
        "EventName": "OFFCOWE_WESPONSE.PF_W3_CODE_WD.W3_MISS_WOCAW_DWAM.SNOOP_NON_DWAM",
        "MSWIndex": "0x1a6,0x1a7",
        "MSWVawue": "0x2004000200",
        "SampweAftewVawue": "100003",
        "UMask": "0x1"
    },
    {
        "BwiefDescwiption": "Counts pwefetch (that bwing data to WWC onwy) code weads",
        "EventCode": "0xB7, 0xBB",
        "EventName": "OFFCOWE_WESPONSE.PF_W3_CODE_WD.W3_MISS_WOCAW_DWAM.SNOOP_NOT_NEEDED",
        "MSWIndex": "0x1a6,0x1a7",
        "MSWVawue": "0x104000200",
        "SampweAftewVawue": "100003",
        "UMask": "0x1"
    },
    {
        "BwiefDescwiption": "Counts pwefetch (that bwing data to WWC onwy) code weads",
        "EventCode": "0xB7, 0xBB",
        "EventName": "OFFCOWE_WESPONSE.PF_W3_CODE_WD.SUPPWIEW_NONE.SNOOP_NON_DWAM",
        "MSWIndex": "0x1a6,0x1a7",
        "MSWVawue": "0x2000020200",
        "SampweAftewVawue": "100003",
        "UMask": "0x1"
    },
    {
        "BwiefDescwiption": "Counts aww pwefetch (that bwing data to WWC onwy) data weads",
        "EventCode": "0xB7, 0xBB",
        "EventName": "OFFCOWE_WESPONSE.PF_W3_DATA_WD.W3_HIT.SNOOP_NON_DWAM",
        "MSWIndex": "0x1a6,0x1a7",
        "MSWVawue": "0x20003C0080",
        "SampweAftewVawue": "100003",
        "UMask": "0x1"
    },
    {
        "BwiefDescwiption": "Counts aww pwefetch (that bwing data to WWC onwy) data weads",
        "EventCode": "0xB7, 0xBB",
        "EventName": "OFFCOWE_WESPONSE.PF_W3_DATA_WD.W3_MISS.SNOOP_HIT_NO_FWD",
        "MSWIndex": "0x1a6,0x1a7",
        "MSWVawue": "0x43C000080",
        "SampweAftewVawue": "100003",
        "UMask": "0x1"
    },
    {
        "BwiefDescwiption": "Counts aww pwefetch (that bwing data to WWC onwy) data weads",
        "EventCode": "0xB7, 0xBB",
        "EventName": "OFFCOWE_WESPONSE.PF_W3_DATA_WD.W3_MISS.SNOOP_MISS",
        "MSWIndex": "0x1a6,0x1a7",
        "MSWVawue": "0x23C000080",
        "SampweAftewVawue": "100003",
        "UMask": "0x1"
    },
    {
        "BwiefDescwiption": "Counts aww pwefetch (that bwing data to WWC onwy) data weads",
        "EventCode": "0xB7, 0xBB",
        "EventName": "OFFCOWE_WESPONSE.PF_W3_DATA_WD.W3_MISS.SNOOP_NONE",
        "MSWIndex": "0x1a6,0x1a7",
        "MSWVawue": "0xBC000080",
        "SampweAftewVawue": "100003",
        "UMask": "0x1"
    },
    {
        "BwiefDescwiption": "Counts aww pwefetch (that bwing data to WWC onwy) data weads",
        "EventCode": "0xB7, 0xBB",
        "EventName": "OFFCOWE_WESPONSE.PF_W3_DATA_WD.W3_MISS.SNOOP_NOT_NEEDED",
        "MSWIndex": "0x1a6,0x1a7",
        "MSWVawue": "0x13C000080",
        "SampweAftewVawue": "100003",
        "UMask": "0x1"
    },
    {
        "BwiefDescwiption": "Counts aww pwefetch (that bwing data to WWC onwy) data weads",
        "EventCode": "0xB7, 0xBB",
        "EventName": "OFFCOWE_WESPONSE.PF_W3_DATA_WD.W3_MISS_WOCAW_DWAM.ANY_SNOOP",
        "MSWIndex": "0x1a6,0x1a7",
        "MSWVawue": "0x3F84000080",
        "SampweAftewVawue": "100003",
        "UMask": "0x1"
    },
    {
        "BwiefDescwiption": "Counts aww pwefetch (that bwing data to WWC onwy) data weads",
        "EventCode": "0xB7, 0xBB",
        "EventName": "OFFCOWE_WESPONSE.PF_W3_DATA_WD.W3_MISS_WOCAW_DWAM.SNOOP_HITM",
        "MSWIndex": "0x1a6,0x1a7",
        "MSWVawue": "0x1004000080",
        "SampweAftewVawue": "100003",
        "UMask": "0x1"
    },
    {
        "BwiefDescwiption": "Counts aww pwefetch (that bwing data to WWC onwy) data weads",
        "EventCode": "0xB7, 0xBB",
        "EventName": "OFFCOWE_WESPONSE.PF_W3_DATA_WD.W3_MISS_WOCAW_DWAM.SNOOP_HIT_NO_FWD",
        "MSWIndex": "0x1a6,0x1a7",
        "MSWVawue": "0x404000080",
        "SampweAftewVawue": "100003",
        "UMask": "0x1"
    },
    {
        "BwiefDescwiption": "Counts aww pwefetch (that bwing data to WWC onwy) data weads",
        "EventCode": "0xB7, 0xBB",
        "EventName": "OFFCOWE_WESPONSE.PF_W3_DATA_WD.W3_MISS_WOCAW_DWAM.SNOOP_MISS",
        "MSWIndex": "0x1a6,0x1a7",
        "MSWVawue": "0x204000080",
        "SampweAftewVawue": "100003",
        "UMask": "0x1"
    },
    {
        "BwiefDescwiption": "Counts aww pwefetch (that bwing data to WWC onwy) data weads",
        "EventCode": "0xB7, 0xBB",
        "EventName": "OFFCOWE_WESPONSE.PF_W3_DATA_WD.W3_MISS_WOCAW_DWAM.SNOOP_NONE",
        "MSWIndex": "0x1a6,0x1a7",
        "MSWVawue": "0x84000080",
        "SampweAftewVawue": "100003",
        "UMask": "0x1"
    },
    {
        "BwiefDescwiption": "Counts aww pwefetch (that bwing data to WWC onwy) data weads",
        "EventCode": "0xB7, 0xBB",
        "EventName": "OFFCOWE_WESPONSE.PF_W3_DATA_WD.W3_MISS_WOCAW_DWAM.SNOOP_NON_DWAM",
        "MSWIndex": "0x1a6,0x1a7",
        "MSWVawue": "0x2004000080",
        "SampweAftewVawue": "100003",
        "UMask": "0x1"
    },
    {
        "BwiefDescwiption": "Counts aww pwefetch (that bwing data to WWC onwy) data weads",
        "EventCode": "0xB7, 0xBB",
        "EventName": "OFFCOWE_WESPONSE.PF_W3_DATA_WD.W3_MISS_WOCAW_DWAM.SNOOP_NOT_NEEDED",
        "MSWIndex": "0x1a6,0x1a7",
        "MSWVawue": "0x104000080",
        "SampweAftewVawue": "100003",
        "UMask": "0x1"
    },
    {
        "BwiefDescwiption": "Counts aww pwefetch (that bwing data to WWC onwy) data weads",
        "EventCode": "0xB7, 0xBB",
        "EventName": "OFFCOWE_WESPONSE.PF_W3_DATA_WD.SUPPWIEW_NONE.SNOOP_NON_DWAM",
        "MSWIndex": "0x1a6,0x1a7",
        "MSWVawue": "0x2000020080",
        "SampweAftewVawue": "100003",
        "UMask": "0x1"
    },
    {
        "BwiefDescwiption": "Counts aww pwefetch (that bwing data to WWC onwy) WFOs",
        "EventCode": "0xB7, 0xBB",
        "EventName": "OFFCOWE_WESPONSE.PF_W3_WFO.W3_HIT.SNOOP_NON_DWAM",
        "MSWIndex": "0x1a6,0x1a7",
        "MSWVawue": "0x20003C0100",
        "SampweAftewVawue": "100003",
        "UMask": "0x1"
    },
    {
        "BwiefDescwiption": "Counts aww pwefetch (that bwing data to WWC onwy) WFOs",
        "EventCode": "0xB7, 0xBB",
        "EventName": "OFFCOWE_WESPONSE.PF_W3_WFO.W3_MISS.SNOOP_HIT_NO_FWD",
        "MSWIndex": "0x1a6,0x1a7",
        "MSWVawue": "0x43C000100",
        "SampweAftewVawue": "100003",
        "UMask": "0x1"
    },
    {
        "BwiefDescwiption": "Counts aww pwefetch (that bwing data to WWC onwy) WFOs",
        "EventCode": "0xB7, 0xBB",
        "EventName": "OFFCOWE_WESPONSE.PF_W3_WFO.W3_MISS.SNOOP_MISS",
        "MSWIndex": "0x1a6,0x1a7",
        "MSWVawue": "0x23C000100",
        "SampweAftewVawue": "100003",
        "UMask": "0x1"
    },
    {
        "BwiefDescwiption": "Counts aww pwefetch (that bwing data to WWC onwy) WFOs",
        "EventCode": "0xB7, 0xBB",
        "EventName": "OFFCOWE_WESPONSE.PF_W3_WFO.W3_MISS.SNOOP_NONE",
        "MSWIndex": "0x1a6,0x1a7",
        "MSWVawue": "0xBC000100",
        "SampweAftewVawue": "100003",
        "UMask": "0x1"
    },
    {
        "BwiefDescwiption": "Counts aww pwefetch (that bwing data to WWC onwy) WFOs",
        "EventCode": "0xB7, 0xBB",
        "EventName": "OFFCOWE_WESPONSE.PF_W3_WFO.W3_MISS.SNOOP_NOT_NEEDED",
        "MSWIndex": "0x1a6,0x1a7",
        "MSWVawue": "0x13C000100",
        "SampweAftewVawue": "100003",
        "UMask": "0x1"
    },
    {
        "BwiefDescwiption": "Counts aww pwefetch (that bwing data to WWC onwy) WFOs",
        "EventCode": "0xB7, 0xBB",
        "EventName": "OFFCOWE_WESPONSE.PF_W3_WFO.W3_MISS_WOCAW_DWAM.ANY_SNOOP",
        "MSWIndex": "0x1a6,0x1a7",
        "MSWVawue": "0x3F84000100",
        "SampweAftewVawue": "100003",
        "UMask": "0x1"
    },
    {
        "BwiefDescwiption": "Counts aww pwefetch (that bwing data to WWC onwy) WFOs",
        "EventCode": "0xB7, 0xBB",
        "EventName": "OFFCOWE_WESPONSE.PF_W3_WFO.W3_MISS_WOCAW_DWAM.SNOOP_HITM",
        "MSWIndex": "0x1a6,0x1a7",
        "MSWVawue": "0x1004000100",
        "SampweAftewVawue": "100003",
        "UMask": "0x1"
    },
    {
        "BwiefDescwiption": "Counts aww pwefetch (that bwing data to WWC onwy) WFOs",
        "EventCode": "0xB7, 0xBB",
        "EventName": "OFFCOWE_WESPONSE.PF_W3_WFO.W3_MISS_WOCAW_DWAM.SNOOP_HIT_NO_FWD",
        "MSWIndex": "0x1a6,0x1a7",
        "MSWVawue": "0x404000100",
        "SampweAftewVawue": "100003",
        "UMask": "0x1"
    },
    {
        "BwiefDescwiption": "Counts aww pwefetch (that bwing data to WWC onwy) WFOs",
        "EventCode": "0xB7, 0xBB",
        "EventName": "OFFCOWE_WESPONSE.PF_W3_WFO.W3_MISS_WOCAW_DWAM.SNOOP_MISS",
        "MSWIndex": "0x1a6,0x1a7",
        "MSWVawue": "0x204000100",
        "SampweAftewVawue": "100003",
        "UMask": "0x1"
    },
    {
        "BwiefDescwiption": "Counts aww pwefetch (that bwing data to WWC onwy) WFOs",
        "EventCode": "0xB7, 0xBB",
        "EventName": "OFFCOWE_WESPONSE.PF_W3_WFO.W3_MISS_WOCAW_DWAM.SNOOP_NONE",
        "MSWIndex": "0x1a6,0x1a7",
        "MSWVawue": "0x84000100",
        "SampweAftewVawue": "100003",
        "UMask": "0x1"
    },
    {
        "BwiefDescwiption": "Counts aww pwefetch (that bwing data to WWC onwy) WFOs",
        "EventCode": "0xB7, 0xBB",
        "EventName": "OFFCOWE_WESPONSE.PF_W3_WFO.W3_MISS_WOCAW_DWAM.SNOOP_NON_DWAM",
        "MSWIndex": "0x1a6,0x1a7",
        "MSWVawue": "0x2004000100",
        "SampweAftewVawue": "100003",
        "UMask": "0x1"
    },
    {
        "BwiefDescwiption": "Counts aww pwefetch (that bwing data to WWC onwy) WFOs",
        "EventCode": "0xB7, 0xBB",
        "EventName": "OFFCOWE_WESPONSE.PF_W3_WFO.W3_MISS_WOCAW_DWAM.SNOOP_NOT_NEEDED",
        "MSWIndex": "0x1a6,0x1a7",
        "MSWVawue": "0x104000100",
        "SampweAftewVawue": "100003",
        "UMask": "0x1"
    },
    {
        "BwiefDescwiption": "Counts aww pwefetch (that bwing data to WWC onwy) WFOs",
        "EventCode": "0xB7, 0xBB",
        "EventName": "OFFCOWE_WESPONSE.PF_W3_WFO.SUPPWIEW_NONE.SNOOP_NON_DWAM",
        "MSWIndex": "0x1a6,0x1a7",
        "MSWVawue": "0x2000020100",
        "SampweAftewVawue": "100003",
        "UMask": "0x1"
    },
    {
        "BwiefDescwiption": "Numbew of times WTM abowt was twiggewed",
        "EventCode": "0xc9",
        "EventName": "WTM_WETIWED.ABOWTED",
        "PEBS": "1",
        "PubwicDescwiption": "Numbew of times WTM abowt was twiggewed .",
        "SampweAftewVawue": "2000003",
        "UMask": "0x4"
    },
    {
        "BwiefDescwiption": "Numbew of times an WTM execution abowted due to vawious memowy events (e.g. wead/wwite capacity and confwicts)",
        "EventCode": "0xc9",
        "EventName": "WTM_WETIWED.ABOWTED_MISC1",
        "PubwicDescwiption": "Numbew of times an WTM abowt was attwibuted to a Memowy condition (See TSX_Memowy event fow additionaw detaiws).",
        "SampweAftewVawue": "2000003",
        "UMask": "0x8"
    },
    {
        "BwiefDescwiption": "Numbew of times an WTM execution abowted due to vawious memowy events (e.g., wead/wwite capacity and confwicts).",
        "EventCode": "0xc9",
        "EventName": "WTM_WETIWED.ABOWTED_MISC2",
        "PubwicDescwiption": "Numbew of times the TSX watchdog signawed an WTM abowt.",
        "SampweAftewVawue": "2000003",
        "UMask": "0x10"
    },
    {
        "BwiefDescwiption": "Numbew of times an WTM execution abowted due to HWE-unfwiendwy instwuctions",
        "EventCode": "0xc9",
        "EventName": "WTM_WETIWED.ABOWTED_MISC3",
        "PubwicDescwiption": "Numbew of times a disawwowed opewation caused an WTM abowt.",
        "SampweAftewVawue": "2000003",
        "UMask": "0x20"
    },
    {
        "BwiefDescwiption": "Numbew of times an WTM execution abowted due to incompatibwe memowy type",
        "EventCode": "0xc9",
        "EventName": "WTM_WETIWED.ABOWTED_MISC4",
        "PubwicDescwiption": "Numbew of times a WTM caused a fauwt.",
        "SampweAftewVawue": "2000003",
        "UMask": "0x40"
    },
    {
        "BwiefDescwiption": "Numbew of times an WTM execution abowted due to none of the pwevious 4 categowies (e.g. intewwupt)",
        "EventCode": "0xc9",
        "EventName": "WTM_WETIWED.ABOWTED_MISC5",
        "PubwicDescwiption": "Numbew of times WTM abowted and was not due to the abowt conditions in subevents 3-6.",
        "SampweAftewVawue": "2000003",
        "UMask": "0x80"
    },
    {
        "BwiefDescwiption": "Numbew of times WTM commit succeeded",
        "EventCode": "0xc9",
        "EventName": "WTM_WETIWED.COMMIT",
        "PubwicDescwiption": "Numbew of times WTM commit succeeded.",
        "SampweAftewVawue": "2000003",
        "UMask": "0x2"
    },
    {
        "BwiefDescwiption": "Numbew of times we entewed an WTM wegion; does not count nested twansactions",
        "EventCode": "0xc9",
        "EventName": "WTM_WETIWED.STAWT",
        "PubwicDescwiption": "Numbew of times we entewed an WTM wegion\n does not count nested twansactions.",
        "SampweAftewVawue": "2000003",
        "UMask": "0x1"
    },
    {
        "BwiefDescwiption": "Counts the numbew of times a cwass of instwuctions that may cause a twansactionaw abowt was executed. Since this is the count of execution, it may not awways cause a twansactionaw abowt.",
        "EventCode": "0x5d",
        "EventName": "TX_EXEC.MISC1",
        "SampweAftewVawue": "2000003",
        "UMask": "0x1"
    },
    {
        "BwiefDescwiption": "Counts the numbew of times a cwass of instwuctions (e.g., vzewouppew) that may cause a twansactionaw abowt was executed inside a twansactionaw wegion",
        "EventCode": "0x5d",
        "EventName": "TX_EXEC.MISC2",
        "PubwicDescwiption": "Unfwiendwy TSX abowt twiggewed by  a vzewouppew instwuction.",
        "SampweAftewVawue": "2000003",
        "UMask": "0x2"
    },
    {
        "BwiefDescwiption": "Counts the numbew of times an instwuction execution caused the twansactionaw nest count suppowted to be exceeded",
        "EventCode": "0x5d",
        "EventName": "TX_EXEC.MISC3",
        "PubwicDescwiption": "Unfwiendwy TSX abowt twiggewed by a nest count that is too deep.",
        "SampweAftewVawue": "2000003",
        "UMask": "0x4"
    },
    {
        "BwiefDescwiption": "Counts the numbew of times a XBEGIN instwuction was executed inside an HWE twansactionaw wegion.",
        "EventCode": "0x5d",
        "EventName": "TX_EXEC.MISC4",
        "PubwicDescwiption": "WTM wegion detected inside HWE.",
        "SampweAftewVawue": "2000003",
        "UMask": "0x8"
    },
    {
        "BwiefDescwiption": "Counts the numbew of times an HWE XACQUIWE instwuction was executed inside an WTM twansactionaw wegion.",
        "EventCode": "0x5d",
        "EventName": "TX_EXEC.MISC5",
        "SampweAftewVawue": "2000003",
        "UMask": "0x10"
    },
    {
        "BwiefDescwiption": "Numbew of times a TSX Abowt was twiggewed due to an evicted wine caused by a twansaction ovewfwow",
        "EventCode": "0x54",
        "EventName": "TX_MEM.ABOWT_CAPACITY_WWITE",
        "PubwicDescwiption": "Numbew of times a TSX Abowt was twiggewed due to an evicted wine caused by a twansaction ovewfwow.",
        "SampweAftewVawue": "2000003",
        "UMask": "0x2"
    },
    {
        "BwiefDescwiption": "Numbew of times a TSX wine had a cache confwict",
        "EventCode": "0x54",
        "EventName": "TX_MEM.ABOWT_CONFWICT",
        "PubwicDescwiption": "Numbew of times a TSX wine had a cache confwict.",
        "SampweAftewVawue": "2000003",
        "UMask": "0x1"
    },
    {
        "BwiefDescwiption": "Numbew of times a TSX Abowt was twiggewed due to wewease/commit but data and addwess mismatch",
        "EventCode": "0x54",
        "EventName": "TX_MEM.ABOWT_HWE_EWISION_BUFFEW_MISMATCH",
        "PubwicDescwiption": "Numbew of times a TSX Abowt was twiggewed due to wewease/commit but data and addwess mismatch.",
        "SampweAftewVawue": "2000003",
        "UMask": "0x10"
    },
    {
        "BwiefDescwiption": "Numbew of times a TSX Abowt was twiggewed due to commit but Wock Buffew not empty",
        "EventCode": "0x54",
        "EventName": "TX_MEM.ABOWT_HWE_EWISION_BUFFEW_NOT_EMPTY",
        "PubwicDescwiption": "Numbew of times a TSX Abowt was twiggewed due to commit but Wock Buffew not empty.",
        "SampweAftewVawue": "2000003",
        "UMask": "0x8"
    },
    {
        "BwiefDescwiption": "Numbew of times a TSX Abowt was twiggewed due to attempting an unsuppowted awignment fwom Wock Buffew",
        "EventCode": "0x54",
        "EventName": "TX_MEM.ABOWT_HWE_EWISION_BUFFEW_UNSUPPOWTED_AWIGNMENT",
        "PubwicDescwiption": "Numbew of times a TSX Abowt was twiggewed due to attempting an unsuppowted awignment fwom Wock Buffew.",
        "SampweAftewVawue": "2000003",
        "UMask": "0x20"
    },
    {
        "BwiefDescwiption": "Numbew of times a TSX Abowt was twiggewed due to a non-wewease/commit stowe to wock",
        "EventCode": "0x54",
        "EventName": "TX_MEM.ABOWT_HWE_STOWE_TO_EWIDED_WOCK",
        "PubwicDescwiption": "Numbew of times a TSX Abowt was twiggewed due to a non-wewease/commit stowe to wock.",
        "SampweAftewVawue": "2000003",
        "UMask": "0x4"
    },
    {
        "BwiefDescwiption": "Numbew of times we couwd not awwocate Wock Buffew",
        "EventCode": "0x54",
        "EventName": "TX_MEM.HWE_EWISION_BUFFEW_FUWW",
        "PubwicDescwiption": "Numbew of times we couwd not awwocate Wock Buffew.",
        "SampweAftewVawue": "2000003",
        "UMask": "0x40"
    }
]
