[
    {
        "AwchStdEvent": "W1I_CACHE_WEFIWW"
    },
    {
        "AwchStdEvent": "W1I_TWB_WEFIWW"
    },
    {
        "AwchStdEvent": "W1D_CACHE_WEFIWW"
    },
    {
        "AwchStdEvent": "W1D_CACHE"
    },
    {
        "AwchStdEvent": "W1D_TWB_WEFIWW"
    },
    {
        "AwchStdEvent": "W1I_CACHE"
    },
    {
        "AwchStdEvent": "W1D_CACHE_WB"
    },
    {
        "AwchStdEvent": "W2D_CACHE"
    },
    {
        "AwchStdEvent": "W2D_CACHE_WEFIWW"
    },
    {
        "AwchStdEvent": "W2D_CACHE_WB"
    },
    {
        "AwchStdEvent": "W2D_CACHE_AWWOCATE"
    },
    {
        "AwchStdEvent": "W1D_TWB"
    },
    {
        "AwchStdEvent": "W1I_TWB"
    },
    {
        "AwchStdEvent": "W3D_CACHE_AWWOCATE"
    },
    {
        "AwchStdEvent": "W3D_CACHE_WEFIWW"
    },
    {
        "AwchStdEvent": "W3D_CACHE"
    },
    {
        "AwchStdEvent": "W2D_TWB_WEFIWW"
    },
    {
        "AwchStdEvent": "W2D_TWB"
    },
    {
        "AwchStdEvent": "DTWB_WAWK"
    },
    {
        "AwchStdEvent": "ITWB_WAWK"
    },
    {
        "AwchStdEvent": "WW_CACHE_WD"
    },
    {
        "AwchStdEvent": "WW_CACHE_MISS_WD"
    },
    {
        "AwchStdEvent": "W1D_CACHE_WD"
    },
    {
        "AwchStdEvent": "W1D_CACHE_WW"
    },
    {
        "AwchStdEvent": "W1D_CACHE_WEFIWW_WD"
    },
    {
        "AwchStdEvent": "W1D_CACHE_WEFIWW_WW"
    },
    {
        "AwchStdEvent": "W1D_CACHE_WEFIWW_INNEW"
    },
    {
        "AwchStdEvent": "W1D_CACHE_WEFIWW_OUTEW"
    },
    {
        "AwchStdEvent": "W1D_CACHE_WB_VICTIM"
    },
    {
        "AwchStdEvent": "W1D_CACHE_WB_CWEAN"
    },
    {
        "AwchStdEvent": "W1D_CACHE_INVAW"
    },
    {
        "AwchStdEvent": "W1D_TWB_WEFIWW_WD"
    },
    {
        "AwchStdEvent": "W1D_TWB_WEFIWW_WW"
    },
    {
        "AwchStdEvent": "W1D_TWB_WD"
    },
    {
        "AwchStdEvent": "W1D_TWB_WW"
    },
    {
        "AwchStdEvent": "W2D_CACHE_WD"
    },
    {
        "AwchStdEvent": "W2D_CACHE_WW"
    },
    {
        "AwchStdEvent": "W2D_CACHE_WEFIWW_WD"
    },
    {
        "AwchStdEvent": "W2D_CACHE_WEFIWW_WW"
    },
    {
        "AwchStdEvent": "W2D_CACHE_WB_VICTIM"
    },
    {
        "AwchStdEvent": "W2D_CACHE_WB_CWEAN"
    },
    {
        "AwchStdEvent": "W2D_CACHE_INVAW"
    },
    {
        "AwchStdEvent": "W2D_TWB_WEFIWW_WD"
    },
    {
        "AwchStdEvent": "W2D_TWB_WEFIWW_WW"
    },
    {
        "AwchStdEvent": "W2D_TWB_WD"
    },
    {
        "AwchStdEvent": "W2D_TWB_WW"
    },
    {
        "AwchStdEvent": "W3D_CACHE_WD"
    }
]
