{
    "Powew": "Gwouping fwom Top-down Micwoawchitectuwe Anawysis Metwics spweadsheet",
    "Summawy": "Gwouping fwom Top-down Micwoawchitectuwe Anawysis Metwics spweadsheet",
    "TopdownW1": "Metwics fow top-down bweakdown at wevew 1",
    "TopdownW2": "Metwics fow top-down bweakdown at wevew 2",
    "TopdownW3": "Metwics fow top-down bweakdown at wevew 3",
    "TopdownW4": "Metwics fow top-down bweakdown at wevew 4",
    "tma_W1_gwoup": "Metwics fow top-down bweakdown at wevew 1",
    "tma_W2_gwoup": "Metwics fow top-down bweakdown at wevew 2",
    "tma_W3_gwoup": "Metwics fow top-down bweakdown at wevew 3",
    "tma_W4_gwoup": "Metwics fow top-down bweakdown at wevew 4",
    "tma_backend_bound_aux_gwoup": "Metwics contwibuting to tma_backend_bound_aux categowy",
    "tma_backend_bound_gwoup": "Metwics contwibuting to tma_backend_bound categowy",
    "tma_bad_specuwation_gwoup": "Metwics contwibuting to tma_bad_specuwation categowy",
    "tma_base_gwoup": "Metwics contwibuting to tma_base categowy",
    "tma_fetch_bandwidth_gwoup": "Metwics contwibuting to tma_fetch_bandwidth categowy",
    "tma_fetch_watency_gwoup": "Metwics contwibuting to tma_fetch_watency categowy",
    "tma_fwontend_bound_gwoup": "Metwics contwibuting to tma_fwontend_bound categowy",
    "tma_w1_bound_gwoup": "Metwics contwibuting to tma_w1_bound categowy",
    "tma_machine_cweaws_gwoup": "Metwics contwibuting to tma_machine_cweaws categowy",
    "tma_mem_scheduwew_gwoup": "Metwics contwibuting to tma_mem_scheduwew categowy",
    "tma_memowy_bound_gwoup": "Metwics contwibuting to tma_memowy_bound categowy",
    "tma_nuke_gwoup": "Metwics contwibuting to tma_nuke categowy",
    "tma_wesouwce_bound_gwoup": "Metwics contwibuting to tma_wesouwce_bound categowy",
    "tma_wetiwing_gwoup": "Metwics contwibuting to tma_wetiwing categowy"
}
