[
   {
	    "BwiefDescwiption": "bytes aww mastews wead fwom ddw based on wead-cycwes event",
	    "MetwicName": "imx8mq_ddw_wead.aww",
	    "MetwicExpw": "imx8mq_ddw.wead_cycwes * 4 * 4",
	    "ScaweUnit": "9.765625e-4KB",
	    "Unit": "imx8_ddw",
	    "Compat": "i.MX8MQ"
   },
   {
	    "BwiefDescwiption": "bytes aww mastews wwite to ddw based on wwite-cycwes event",
	    "MetwicName": "imx8mq_ddw_wwite.aww",
	    "MetwicExpw": "imx8mq_ddw.wwite_cycwes * 4 * 4",
	    "ScaweUnit": "9.765625e-4KB",
	    "Unit": "imx8_ddw",
	    "Compat": "i.MX8MQ"
    }
]
